combinational_circuits/fullsub/fs.v
module halfsub(
input a,b,
output diff,borrow);
assign diff = a^b;
assign borrow = ~a&b;
endmodule


module fullsub(
input a,b,c,
output diff,borrow);
wire s1,c1,c2;
halfsub ha1(
.a(a),
.b(b),
.diff(s1),
.borrow(c1));
halfsub ha2(
.a(s1),
.b(c),
.diff(diff),
.borrow(c2)
);
assign borrow = c1|c2;
endmodule

02combinational_circuits/fullsub/tb_fullsub.v
module tb_fullsub;
reg a,b,c;
wire diff,borrow;
fullsub uut(
.a(a),
.b(b),
.c(c),
.diff(diff),
.borrow(borrow)
);
initial begin 
$dumpfile("fullsub.vcd");
$dumpvars(0,tb_fullsub);
$monitor("Time=%0t| a=%b|b=%b|c=%b|diff=%b|borrow=%b",$time,a,b,c,diff,borrow);
a=0;b=0;c=0;#10;
a=0;b=0;c=1;#10;
a=0;b=1;c=0;#10;
a=0;b=1;c=1;#10;
a=1;b=0;c=0;#10;
a=1;b=0;c=1;#10;
a=1;b=1;c=0;#10;
a=1;b=1;c=1;#10;
$finish;
end
endmodule

combinational_circuits/fullsub/fullsub.vcd
$date
	Tue Feb  3 17:11:30 2026
$end
$version
	Icarus Verilog
$end
$timescale
	1s
$end
$scope module tb_fullsub $end
$var wire 1 ! diff $end
$var wire 1 " borrow $end
$var reg 1 # a $end
$var reg 1 $ b $end
$var reg 1 % c $end
$scope module uut $end
$var wire 1 # a $end
$var wire 1 $ b $end
$var wire 1 " borrow $end
$var wire 1 % c $end
$var wire 1 & s1 $end
$var wire 1 ! diff $end
$var wire 1 ' c2 $end
$var wire 1 ( c1 $end
$scope module ha1 $end
$var wire 1 # a $end
$var wire 1 $ b $end
$var wire 1 ( borrow $end
$var wire 1 & diff $end
$upscope $end
$scope module ha2 $end
$var wire 1 & a $end
$var wire 1 % b $end
$var wire 1 ' borrow $end
$var wire 1 ! diff $end
$upscope $end
$upscope $end
$upscope $end
$enddefinitions $end
$comment Show the parameter values. $end
$dumpall
$end
#0
$dumpvars
0(
0'
0&
0%
0$
0#
0"
0!
$end
#10
1"
1!
1'
1%
#20
0'
1&
1(
0%
1$
#30
0!
1%
#40
0"
1!
0(
0%
0$
1#
#50
0!
1%
#60
0&
0%
1$
#70
1"
1!
1'
1%
