06Assignments/assignment1/mag_com/mag_com.v
module mag_cmp(
input [1:0]a,
input [1:0]b,
output out0,out1,out2);
wire j,k,c,d,w,x,y,z,e,f,g,h,i;
not(w,a[1]);
not(x,a[0]);
not(y,b[1]);
not(z,b[0]);
and(j,a[1],y);
and(k,y,z,a[0]);
and(c,z,a[1],a[0]);
or(out0,j,k,c);
and(d,w,x,b[0]);
and(e,b[1],w);
and(l,x,b[1],b[0]);
or(out1,d,e,l);
and(f,w,x,y,z);
and(g,w,a[0],y,b[0]);
and(h,a[1],a[0],b[1],b[0]);
and(i,a[1],x,b[1],z);
or(out2,f,g,h,i);
endmodule

06Assignments/assignment1/mag_com/tb_mag.v
module tb_mag;
reg [1:0]a,b;
wire [2:0]out;
mag_cmp uut(
.a(a),
.b(b),
.out0(out0),
.out1(out1),
.out2(out2)
);
initial begin
$dumpfile("magcmp.vcd");
$dumpvars(0,tb_mag);
a=2'b00;b=2'b00;#10;
a=2'b00;b=2'b01;#10;
a=2'b00;b=2'b10;#10;
a=2'b00;b=2'b11;#10;
a=2'b01;b=2'b00;#10;
a=2'b01;b=2'b01;#10;
a=2'b01;b=2'b10;#10;
a=2'b01;b=2'b11;#10;
a=2'b10;b=2'b00;#00;
a=2'b10;b=2'b01;#10;
a=2'b10;b=2'b10;#10;
a=2'b10;b=2'b11;#10;
a=2'b11;b=2'b00;#10;
a=2'b11;b=2'b01;#10;
a=2'b11;b=2'b10;#10;
a=2'b11;b=2'b11;#10;
$finish;
end
endmodule

06Assignments/assignment1/mag_com/magcmp.vcd
$date
	Thu Feb 12 10:51:34 2026
$end
$version
	Icarus Verilog
$end
$timescale
	1s
$end
$scope module tb_mag $end
$var wire 1 ! out2 $end
$var wire 1 " out1 $end
$var wire 1 # out0 $end
$var reg 2 $ a [1:0] $end
$var reg 2 % b [1:0] $end
$scope module uut $end
$var wire 2 & a [1:0] $end
$var wire 2 ' b [1:0] $end
$var wire 1 ( c $end
$var wire 1 ) d $end
$var wire 1 * e $end
$var wire 1 + f $end
$var wire 1 , g $end
$var wire 1 - h $end
$var wire 1 . i $end
$var wire 1 / j $end
$var wire 1 0 k $end
$var wire 1 1 l $end
$var wire 1 # out0 $end
$var wire 1 " out1 $end
$var wire 1 ! out2 $end
$var wire 1 2 w $end
$var wire 1 3 x $end
$var wire 1 4 y $end
$var wire 1 5 z $end
$upscope $end
$upscope $end
$enddefinitions $end
$comment Show the parameter values. $end
$dumpall
$end
#0
$dumpvars
15
14
13
12
01
00
0/
0.
0-
0,
1+
0*
0)
0(
b0 '
b0 &
b0 %
b0 $
0#
0"
1!
$end
#10
0!
0+
1"
05
1)
b1 %
b1 '
#20
04
15
0)
1*
b10 %
b10 '
#30
05
1)
11
b11 %
b11 '
#40
1#
10
0"
14
15
0)
0*
01
03
b0 %
b0 '
b1 $
b1 &
#50
0#
00
1!
05
1,
b1 %
b1 '
#60
1"
0!
04
15
1*
0,
b10 %
b10 '
#70
05
b11 %
b11 '
#80
1#
1/
0"
14
05
0*
02
13
b1 %
b1 '
b10 $
b10 &
#90
0#
1!
0/
1.
04
15
b10 %
b10 '
#100
0!
0.
1"
05
11
b11 %
b11 '
#110
1#
1/
10
1(
0"
14
15
01
03
b0 %
b0 '
b11 $
b11 &
#120
00
0(
05
b1 %
b1 '
#130
0/
1(
04
15
b10 %
b10 '
#140
0#
0(
1!
05
1-
b11 %
b11 '
