10memory/dual_port/asyn/dual.v
module dual #(parameter depth=64, address = 6, width = 8)(
input clk,
input [width-1:0]data_a,data_b,
input [address-1:0]addr_a,addr_b,
input we_a,we_b,
output reg [width-1:0]q_a,q_b);

reg [width-1:0] ram[depth-1:0];

always @(*)
begin
if(we_a)
ram[addr_a] <= data_a;

if(we_b)
ram[addr_b] <= data_b;
end

always @(*)
begin
q_a <= ram[addr_a];
q_b <= ram[addr_b];
end
	

endmodule

10memory/dual_port/asyn/tb.v
module tb;
parameter width=8,depth=64,address=6;
reg clk;
reg [width-1:0]data_a,data_b;
reg [address-1:0]addr_a,addr_b;
reg we_a,we_b;
wire [width-1:0]q_a,q_b;
dual #(.width(width),.depth(depth),.address(address)) uut(
	.clk(clk),
	.data_a(data_a),
	.data_b(data_b),
	.addr_a(addr_a),
	.addr_b(addr_b),
	.we_a(we_a),
	.we_b(we_b),
	.q_a(q_a),
	.q_b(q_b));

always #5 clk = ~clk;
integer i;
reg [width-1:0] golden [depth-1:0];
reg [width-1:0] expected_a,expected_b;
initial begin
clk=0;
we_a=0;we_b=0;
data_a=0;data_b=0;
addr_a=0;addr_b=0;
// write
for(i=0;i<depth;i=i+1)
begin
we_a=1;
we_b=1;

addr_a=i;
addr_b= (i+1)%depth;

data_a= i+5;
data_b=i+10;

golden[i]=i+5;
golden[i+1] =i+10;
#10;
end

//read
for(i=0;i<depth;i=i+1)
begin
we_a=0;
we_b=0;

addr_a=i;
addr_b=(i+1)%64;
#10;
end
$finish;
end

always @(posedge clk)
begin
	expected_a = golden[i];
	expected_b = golden[i+1];

if(expected_a == q_a)
	$display("**Ram is working**|Time=%0t|clk=%b|we_a=%d|data_a=%d|addr_a=%d|expected=%d|actual=%d",$time,clk,we_a,data_a,addr_a,expected_a,q_a);
else
	$display("Ram is not working|Time=%0t|clk=%b|we_a=%d|data_a=%d|addr_a=%d|expected=%d|actual=%d",$time,clk,we_a,data_a,addr_a,expected_a,q_a);
if(expected_b == q_b)
        $display("**Ram is working**|Time=%0t|clk=%b|we_b=%d|data_b=%d|addr_b=%d|expected=%d|q_b=%d",$time,clk,we_b,data_b,addr_b,expected_b,q_b);
else
        $display("Ram is not working|Time=%0t|clk=%b|we_b=%d|data_b=%d|addr_b=%d|expected=%d|q_b=%d",$time,clk,we_b,data_b,addr_b,expected_b,q_b);

end


initial begin
	$dumpfile("ram.vcd");
	$dumpvars(0,tb);
end

endmodule

10memory/dual_port/asyn/ram.vcd
$date
	Sat Mar  7 15:22:44 2026
$end
$version
	Icarus Verilog
$end
$timescale
	1s
$end
$scope module tb $end
$var wire 8 ! q_b [7:0] $end
$var wire 8 " q_a [7:0] $end
$var parameter 32 # address $end
$var parameter 32 $ depth $end
$var parameter 32 % width $end
$var reg 6 & addr_a [5:0] $end
$var reg 6 ' addr_b [5:0] $end
$var reg 1 ( clk $end
$var reg 8 ) data_a [7:0] $end
$var reg 8 * data_b [7:0] $end
$var reg 8 + expected_a [7:0] $end
$var reg 8 , expected_b [7:0] $end
$var reg 1 - we_a $end
$var reg 1 . we_b $end
$var integer 32 / i [31:0] $end
$scope module uut $end
$var wire 6 0 addr_a [5:0] $end
$var wire 6 1 addr_b [5:0] $end
$var wire 1 ( clk $end
$var wire 8 2 data_a [7:0] $end
$var wire 8 3 data_b [7:0] $end
$var wire 1 - we_a $end
$var wire 1 . we_b $end
$var parameter 32 4 address $end
$var parameter 32 5 depth $end
$var parameter 32 6 width $end
$var reg 8 7 q_a [7:0] $end
$var reg 8 8 q_b [7:0] $end
$upscope $end
$upscope $end
$enddefinitions $end
$comment Show the parameter values. $end
$dumpall
b1000 6
b1000000 5
b110 4
b1000 %
b1000000 $
b110 #
$end
#0
$dumpvars
b1010 8
b101 7
b1010 3
b101 2
b1 1
b0 0
b0 /
1.
1-
bx ,
bx +
b1010 *
b101 )
0(
b1 '
b0 &
b101 "
b1010 !
$end
#5
b1010 ,
b101 +
1(
#10
b1011 !
b1011 8
b110 "
b110 7
0(
b1011 *
b1011 3
b110 )
b110 2
b10 '
b10 1
b1 &
b1 0
b1 /
#15
b1011 ,
b110 +
1(
#20
b1100 !
b1100 8
b111 "
b111 7
0(
b1100 *
b1100 3
b111 )
b111 2
b11 '
b11 1
b10 &
b10 0
b10 /
#25
b1100 ,
b111 +
1(
#30
b1101 !
b1101 8
b1000 "
b1000 7
0(
b1101 *
b1101 3
b1000 )
b1000 2
b100 '
b100 1
b11 &
b11 0
b11 /
#35
b1101 ,
b1000 +
1(
#40
b1110 !
b1110 8
b1001 "
b1001 7
0(
b1110 *
b1110 3
b1001 )
b1001 2
b101 '
b101 1
b100 &
b100 0
b100 /
#45
b1110 ,
b1001 +
1(
#50
b1111 !
b1111 8
b1010 "
b1010 7
0(
b1111 *
b1111 3
b1010 )
b1010 2
b110 '
b110 1
b101 &
b101 0
b101 /
#55
b1111 ,
b1010 +
1(
#60
b10000 !
b10000 8
b1011 "
b1011 7
0(
b10000 *
b10000 3
b1011 )
b1011 2
b111 '
b111 1
b110 &
b110 0
b110 /
#65
b10000 ,
b1011 +
1(
#70
b10001 !
b10001 8
b1100 "
b1100 7
0(
b10001 *
b10001 3
b1100 )
b1100 2
b1000 '
b1000 1
b111 &
b111 0
b111 /
#75
b10001 ,
b1100 +
1(
#80
b10010 !
b10010 8
b1101 "
b1101 7
0(
b10010 *
b10010 3
b1101 )
b1101 2
b1001 '
b1001 1
b1000 &
b1000 0
b1000 /
#85
b10010 ,
b1101 +
1(
#90
b10011 !
b10011 8
b1110 "
b1110 7
0(
b10011 *
b10011 3
b1110 )
b1110 2
b1010 '
b1010 1
b1001 &
b1001 0
b1001 /
#95
b10011 ,
b1110 +
1(
#100
b10100 !
b10100 8
b1111 "
b1111 7
0(
b10100 *
b10100 3
b1111 )
b1111 2
b1011 '
b1011 1
b1010 &
b1010 0
b1010 /
#105
b10100 ,
b1111 +
1(
#110
b10101 !
b10101 8
b10000 "
b10000 7
0(
b10101 *
b10101 3
b10000 )
b10000 2
b1100 '
b1100 1
b1011 &
b1011 0
b1011 /
#115
b10101 ,
b10000 +
1(
#120
b10110 !
b10110 8
b10001 "
b10001 7
0(
b10110 *
b10110 3
b10001 )
b10001 2
b1101 '
b1101 1
b1100 &
b1100 0
b1100 /
#125
b10110 ,
b10001 +
1(
#130
b10111 !
b10111 8
b10010 "
b10010 7
0(
b10111 *
b10111 3
b10010 )
b10010 2
b1110 '
b1110 1
b1101 &
b1101 0
b1101 /
#135
b10111 ,
b10010 +
1(
#140
b11000 !
b11000 8
b10011 "
b10011 7
0(
b11000 *
b11000 3
b10011 )
b10011 2
b1111 '
b1111 1
b1110 &
b1110 0
b1110 /
#145
b11000 ,
b10011 +
1(
#150
b11001 !
b11001 8
b10100 "
b10100 7
0(
b11001 *
b11001 3
b10100 )
b10100 2
b10000 '
b10000 1
b1111 &
b1111 0
b1111 /
#155
b11001 ,
b10100 +
1(
#160
b11010 !
b11010 8
b10101 "
b10101 7
0(
b11010 *
b11010 3
b10101 )
b10101 2
b10001 '
b10001 1
b10000 &
b10000 0
b10000 /
#165
b11010 ,
b10101 +
1(
#170
b11011 !
b11011 8
b10110 "
b10110 7
0(
b11011 *
b11011 3
b10110 )
b10110 2
b10010 '
b10010 1
b10001 &
b10001 0
b10001 /
#175
b11011 ,
b10110 +
1(
#180
b11100 !
b11100 8
b10111 "
b10111 7
0(
b11100 *
b11100 3
b10111 )
b10111 2
b10011 '
b10011 1
b10010 &
b10010 0
b10010 /
#185
b11100 ,
b10111 +
1(
#190
b11101 !
b11101 8
b11000 "
b11000 7
0(
b11101 *
b11101 3
b11000 )
b11000 2
b10100 '
b10100 1
b10011 &
b10011 0
b10011 /
#195
b11101 ,
b11000 +
1(
#200
b11110 !
b11110 8
b11001 "
b11001 7
0(
b11110 *
b11110 3
b11001 )
b11001 2
b10101 '
b10101 1
b10100 &
b10100 0
b10100 /
#205
b11110 ,
b11001 +
1(
#210
b11111 !
b11111 8
b11010 "
b11010 7
0(
b11111 *
b11111 3
b11010 )
b11010 2
b10110 '
b10110 1
b10101 &
b10101 0
b10101 /
#215
b11111 ,
b11010 +
1(
#220
b100000 !
b100000 8
b11011 "
b11011 7
0(
b100000 *
b100000 3
b11011 )
b11011 2
b10111 '
b10111 1
b10110 &
b10110 0
b10110 /
#225
b100000 ,
b11011 +
1(
#230
b100001 !
b100001 8
b11100 "
b11100 7
0(
b100001 *
b100001 3
b11100 )
b11100 2
b11000 '
b11000 1
b10111 &
b10111 0
b10111 /
#235
b100001 ,
b11100 +
1(
#240
b100010 !
b100010 8
b11101 "
b11101 7
0(
b100010 *
b100010 3
b11101 )
b11101 2
b11001 '
b11001 1
b11000 &
b11000 0
b11000 /
#245
b100010 ,
b11101 +
1(
#250
b100011 !
b100011 8
b11110 "
b11110 7
0(
b100011 *
b100011 3
b11110 )
b11110 2
b11010 '
b11010 1
b11001 &
b11001 0
b11001 /
#255
b100011 ,
b11110 +
1(
#260
b100100 !
b100100 8
b11111 "
b11111 7
0(
b100100 *
b100100 3
b11111 )
b11111 2
b11011 '
b11011 1
b11010 &
b11010 0
b11010 /
#265
b100100 ,
b11111 +
1(
#270
b100101 !
b100101 8
b100000 "
b100000 7
0(
b100101 *
b100101 3
b100000 )
b100000 2
b11100 '
b11100 1
b11011 &
b11011 0
b11011 /
#275
b100101 ,
b100000 +
1(
#280
b100110 !
b100110 8
b100001 "
b100001 7
0(
b100110 *
b100110 3
b100001 )
b100001 2
b11101 '
b11101 1
b11100 &
b11100 0
b11100 /
#285
b100110 ,
b100001 +
1(
#290
b100111 !
b100111 8
b100010 "
b100010 7
0(
b100111 *
b100111 3
b100010 )
b100010 2
b11110 '
b11110 1
b11101 &
b11101 0
b11101 /
#295
b100111 ,
b100010 +
1(
#300
b101000 !
b101000 8
b100011 "
b100011 7
0(
b101000 *
b101000 3
b100011 )
b100011 2
b11111 '
b11111 1
b11110 &
b11110 0
b11110 /
#305
b101000 ,
b100011 +
1(
#310
b101001 !
b101001 8
b100100 "
b100100 7
0(
b101001 *
b101001 3
b100100 )
b100100 2
b100000 '
b100000 1
b11111 &
b11111 0
b11111 /
#315
b101001 ,
b100100 +
1(
#320
b101010 !
b101010 8
b100101 "
b100101 7
0(
b101010 *
b101010 3
b100101 )
b100101 2
b100001 '
b100001 1
b100000 &
b100000 0
b100000 /
#325
b101010 ,
b100101 +
1(
#330
b101011 !
b101011 8
b100110 "
b100110 7
0(
b101011 *
b101011 3
b100110 )
b100110 2
b100010 '
b100010 1
b100001 &
b100001 0
b100001 /
#335
b101011 ,
b100110 +
1(
#340
b101100 !
b101100 8
b100111 "
b100111 7
0(
b101100 *
b101100 3
b100111 )
b100111 2
b100011 '
b100011 1
b100010 &
b100010 0
b100010 /
#345
b101100 ,
b100111 +
1(
#350
b101101 !
b101101 8
b101000 "
b101000 7
0(
b101101 *
b101101 3
b101000 )
b101000 2
b100100 '
b100100 1
b100011 &
b100011 0
b100011 /
#355
b101101 ,
b101000 +
1(
#360
b101110 !
b101110 8
b101001 "
b101001 7
0(
b101110 *
b101110 3
b101001 )
b101001 2
b100101 '
b100101 1
b100100 &
b100100 0
b100100 /
#365
b101110 ,
b101001 +
1(
#370
b101111 !
b101111 8
b101010 "
b101010 7
0(
b101111 *
b101111 3
b101010 )
b101010 2
b100110 '
b100110 1
b100101 &
b100101 0
b100101 /
#375
b101111 ,
b101010 +
1(
#380
b110000 !
b110000 8
b101011 "
b101011 7
0(
b110000 *
b110000 3
b101011 )
b101011 2
b100111 '
b100111 1
b100110 &
b100110 0
b100110 /
#385
b110000 ,
b101011 +
1(
#390
b110001 !
b110001 8
b101100 "
b101100 7
0(
b110001 *
b110001 3
b101100 )
b101100 2
b101000 '
b101000 1
b100111 &
b100111 0
b100111 /
#395
b110001 ,
b101100 +
1(
#400
b110010 !
b110010 8
b101101 "
b101101 7
0(
b110010 *
b110010 3
b101101 )
b101101 2
b101001 '
b101001 1
b101000 &
b101000 0
b101000 /
#405
b110010 ,
b101101 +
1(
#410
b110011 !
b110011 8
b101110 "
b101110 7
0(
b110011 *
b110011 3
b101110 )
b101110 2
b101010 '
b101010 1
b101001 &
b101001 0
b101001 /
#415
b110011 ,
b101110 +
1(
#420
b110100 !
b110100 8
b101111 "
b101111 7
0(
b110100 *
b110100 3
b101111 )
b101111 2
b101011 '
b101011 1
b101010 &
b101010 0
b101010 /
#425
b110100 ,
b101111 +
1(
#430
b110101 !
b110101 8
b110000 "
b110000 7
0(
b110101 *
b110101 3
b110000 )
b110000 2
b101100 '
b101100 1
b101011 &
b101011 0
b101011 /
#435
b110101 ,
b110000 +
1(
#440
b110110 !
b110110 8
b110001 "
b110001 7
0(
b110110 *
b110110 3
b110001 )
b110001 2
b101101 '
b101101 1
b101100 &
b101100 0
b101100 /
#445
b110110 ,
b110001 +
1(
#450
b110111 !
b110111 8
b110010 "
b110010 7
0(
b110111 *
b110111 3
b110010 )
b110010 2
b101110 '
b101110 1
b101101 &
b101101 0
b101101 /
#455
b110111 ,
b110010 +
1(
#460
b111000 !
b111000 8
b110011 "
b110011 7
0(
b111000 *
b111000 3
b110011 )
b110011 2
b101111 '
b101111 1
b101110 &
b101110 0
b101110 /
#465
b111000 ,
b110011 +
1(
#470
b111001 !
b111001 8
b110100 "
b110100 7
0(
b111001 *
b111001 3
b110100 )
b110100 2
b110000 '
b110000 1
b101111 &
b101111 0
b101111 /
#475
b111001 ,
b110100 +
1(
#480
b111010 !
b111010 8
b110101 "
b110101 7
0(
b111010 *
b111010 3
b110101 )
b110101 2
b110001 '
b110001 1
b110000 &
b110000 0
b110000 /
#485
b111010 ,
b110101 +
1(
#490
b111011 !
b111011 8
b110110 "
b110110 7
0(
b111011 *
b111011 3
b110110 )
b110110 2
b110010 '
b110010 1
b110001 &
b110001 0
b110001 /
#495
b111011 ,
b110110 +
1(
#500
b111100 !
b111100 8
b110111 "
b110111 7
0(
b111100 *
b111100 3
b110111 )
b110111 2
b110011 '
b110011 1
b110010 &
b110010 0
b110010 /
#505
b111100 ,
b110111 +
1(
#510
b111101 !
b111101 8
b111000 "
b111000 7
0(
b111101 *
b111101 3
b111000 )
b111000 2
b110100 '
b110100 1
b110011 &
b110011 0
b110011 /
#515
b111101 ,
b111000 +
1(
#520
b111110 !
b111110 8
b111001 "
b111001 7
0(
b111110 *
b111110 3
b111001 )
b111001 2
b110101 '
b110101 1
b110100 &
b110100 0
b110100 /
#525
b111110 ,
b111001 +
1(
#530
b111111 !
b111111 8
b111010 "
b111010 7
0(
b111111 *
b111111 3
b111010 )
b111010 2
b110110 '
b110110 1
b110101 &
b110101 0
b110101 /
#535
b111111 ,
b111010 +
1(
#540
b1000000 !
b1000000 8
b111011 "
b111011 7
0(
b1000000 *
b1000000 3
b111011 )
b111011 2
b110111 '
b110111 1
b110110 &
b110110 0
b110110 /
#545
b1000000 ,
b111011 +
1(
#550
b1000001 !
b1000001 8
b111100 "
b111100 7
0(
b1000001 *
b1000001 3
b111100 )
b111100 2
b111000 '
b111000 1
b110111 &
b110111 0
b110111 /
#555
b1000001 ,
b111100 +
1(
#560
b1000010 !
b1000010 8
b111101 "
b111101 7
0(
b1000010 *
b1000010 3
b111101 )
b111101 2
b111001 '
b111001 1
b111000 &
b111000 0
b111000 /
#565
b1000010 ,
b111101 +
1(
#570
b1000011 !
b1000011 8
b111110 "
b111110 7
0(
b1000011 *
b1000011 3
b111110 )
b111110 2
b111010 '
b111010 1
b111001 &
b111001 0
b111001 /
#575
b1000011 ,
b111110 +
1(
#580
b1000100 !
b1000100 8
b111111 "
b111111 7
0(
b1000100 *
b1000100 3
b111111 )
b111111 2
b111011 '
b111011 1
b111010 &
b111010 0
b111010 /
#585
b1000100 ,
b111111 +
1(
#590
b1000101 !
b1000101 8
b1000000 "
b1000000 7
0(
b1000101 *
b1000101 3
b1000000 )
b1000000 2
b111100 '
b111100 1
b111011 &
b111011 0
b111011 /
#595
b1000101 ,
b1000000 +
1(
#600
b1000110 !
b1000110 8
b1000001 "
b1000001 7
0(
b1000110 *
b1000110 3
b1000001 )
b1000001 2
b111101 '
b111101 1
b111100 &
b111100 0
b111100 /
#605
b1000110 ,
b1000001 +
1(
#610
b1000111 !
b1000111 8
b1000010 "
b1000010 7
0(
b1000111 *
b1000111 3
b1000010 )
b1000010 2
b111110 '
b111110 1
b111101 &
b111101 0
b111101 /
#615
b1000111 ,
b1000010 +
1(
#620
b1001000 !
b1001000 8
b1000011 "
b1000011 7
0(
b1001000 *
b1001000 3
b1000011 )
b1000011 2
b111111 '
b111111 1
b111110 &
b111110 0
b111110 /
#625
b1001000 ,
b1000011 +
1(
#630
b1001001 !
b1001001 8
b1000100 "
b1000100 7
0(
b1001001 *
b1001001 3
b1000100 )
b1000100 2
b0 '
b0 1
b111111 &
b111111 0
b111111 /
#635
bx ,
b1000100 +
1(
#640
b110 !
b110 8
b1001001 "
b1001001 7
0(
b1 '
b1 1
b0 &
b0 0
0.
0-
b0 /
#645
b110 ,
b101 +
1(
#650
b111 !
b111 8
b110 "
b110 7
0(
b10 '
b10 1
b1 &
b1 0
b1 /
#655
b111 ,
b110 +
1(
#660
b1000 !
b1000 8
b111 "
b111 7
0(
b11 '
b11 1
b10 &
b10 0
b10 /
#665
b1000 ,
b111 +
1(
#670
b1001 !
b1001 8
b1000 "
b1000 7
0(
b100 '
b100 1
b11 &
b11 0
b11 /
#675
b1001 ,
b1000 +
1(
#680
b1010 !
b1010 8
b1001 "
b1001 7
0(
b101 '
b101 1
b100 &
b100 0
b100 /
#685
b1010 ,
b1001 +
1(
#690
b1011 !
b1011 8
b1010 "
b1010 7
0(
b110 '
b110 1
b101 &
b101 0
b101 /
#695
b1011 ,
b1010 +
1(
#700
b1100 !
b1100 8
b1011 "
b1011 7
0(
b111 '
b111 1
b110 &
b110 0
b110 /
#705
b1100 ,
b1011 +
1(
#710
b1101 !
b1101 8
b1100 "
b1100 7
0(
b1000 '
b1000 1
b111 &
b111 0
b111 /
#715
b1101 ,
b1100 +
1(
#720
b1110 !
b1110 8
b1101 "
b1101 7
0(
b1001 '
b1001 1
b1000 &
b1000 0
b1000 /
#725
b1110 ,
b1101 +
1(
#730
b1111 !
b1111 8
b1110 "
b1110 7
0(
b1010 '
b1010 1
b1001 &
b1001 0
b1001 /
#735
b1111 ,
b1110 +
1(
#740
b10000 !
b10000 8
b1111 "
b1111 7
0(
b1011 '
b1011 1
b1010 &
b1010 0
b1010 /
#745
b10000 ,
b1111 +
1(
#750
b10001 !
b10001 8
b10000 "
b10000 7
0(
b1100 '
b1100 1
b1011 &
b1011 0
b1011 /
#755
b10001 ,
b10000 +
1(
#760
b10010 !
b10010 8
b10001 "
b10001 7
0(
b1101 '
b1101 1
b1100 &
b1100 0
b1100 /
#765
b10010 ,
b10001 +
1(
#770
b10011 !
b10011 8
b10010 "
b10010 7
0(
b1110 '
b1110 1
b1101 &
b1101 0
b1101 /
#775
b10011 ,
b10010 +
1(
#780
b10100 !
b10100 8
b10011 "
b10011 7
0(
b1111 '
b1111 1
b1110 &
b1110 0
b1110 /
#785
b10100 ,
b10011 +
1(
#790
b10101 !
b10101 8
b10100 "
b10100 7
0(
b10000 '
b10000 1
b1111 &
b1111 0
b1111 /
#795
b10101 ,
b10100 +
1(
#800
b10110 !
b10110 8
b10101 "
b10101 7
0(
b10001 '
b10001 1
b10000 &
b10000 0
b10000 /
#805
b10110 ,
b10101 +
1(
#810
b10111 !
b10111 8
b10110 "
b10110 7
0(
b10010 '
b10010 1
b10001 &
b10001 0
b10001 /
#815
b10111 ,
b10110 +
1(
#820
b11000 !
b11000 8
b10111 "
b10111 7
0(
b10011 '
b10011 1
b10010 &
b10010 0
b10010 /
#825
b11000 ,
b10111 +
1(
#830
b11001 !
b11001 8
b11000 "
b11000 7
0(
b10100 '
b10100 1
b10011 &
b10011 0
b10011 /
#835
b11001 ,
b11000 +
1(
#840
b11010 !
b11010 8
b11001 "
b11001 7
0(
b10101 '
b10101 1
b10100 &
b10100 0
b10100 /
#845
b11010 ,
b11001 +
1(
#850
b11011 !
b11011 8
b11010 "
b11010 7
0(
b10110 '
b10110 1
b10101 &
b10101 0
b10101 /
#855
b11011 ,
b11010 +
1(
#860
b11100 !
b11100 8
b11011 "
b11011 7
0(
b10111 '
b10111 1
b10110 &
b10110 0
b10110 /
#865
b11100 ,
b11011 +
1(
#870
b11101 !
b11101 8
b11100 "
b11100 7
0(
b11000 '
b11000 1
b10111 &
b10111 0
b10111 /
#875
b11101 ,
b11100 +
1(
#880
b11110 !
b11110 8
b11101 "
b11101 7
0(
b11001 '
b11001 1
b11000 &
b11000 0
b11000 /
#885
b11110 ,
b11101 +
1(
#890
b11111 !
b11111 8
b11110 "
b11110 7
0(
b11010 '
b11010 1
b11001 &
b11001 0
b11001 /
#895
b11111 ,
b11110 +
1(
#900
b100000 !
b100000 8
b11111 "
b11111 7
0(
b11011 '
b11011 1
b11010 &
b11010 0
b11010 /
#905
b100000 ,
b11111 +
1(
#910
b100001 !
b100001 8
b100000 "
b100000 7
0(
b11100 '
b11100 1
b11011 &
b11011 0
b11011 /
#915
b100001 ,
b100000 +
1(
#920
b100010 !
b100010 8
b100001 "
b100001 7
0(
b11101 '
b11101 1
b11100 &
b11100 0
b11100 /
#925
b100010 ,
b100001 +
1(
#930
b100011 !
b100011 8
b100010 "
b100010 7
0(
b11110 '
b11110 1
b11101 &
b11101 0
b11101 /
#935
b100011 ,
b100010 +
1(
#940
b100100 !
b100100 8
b100011 "
b100011 7
0(
b11111 '
b11111 1
b11110 &
b11110 0
b11110 /
#945
b100100 ,
b100011 +
1(
#950
b100101 !
b100101 8
b100100 "
b100100 7
0(
b100000 '
b100000 1
b11111 &
b11111 0
b11111 /
#955
b100101 ,
b100100 +
1(
#960
b100110 !
b100110 8
b100101 "
b100101 7
0(
b100001 '
b100001 1
b100000 &
b100000 0
b100000 /
#965
b100110 ,
b100101 +
1(
#970
b100111 !
b100111 8
b100110 "
b100110 7
0(
b100010 '
b100010 1
b100001 &
b100001 0
b100001 /
#975
b100111 ,
b100110 +
1(
#980
b101000 !
b101000 8
b100111 "
b100111 7
0(
b100011 '
b100011 1
b100010 &
b100010 0
b100010 /
#985
b101000 ,
b100111 +
1(
#990
b101001 !
b101001 8
b101000 "
b101000 7
0(
b100100 '
b100100 1
b100011 &
b100011 0
b100011 /
#995
b101001 ,
b101000 +
1(
#1000
b101010 !
b101010 8
b101001 "
b101001 7
0(
b100101 '
b100101 1
b100100 &
b100100 0
b100100 /
#1005
b101010 ,
b101001 +
1(
#1010
b101011 !
b101011 8
b101010 "
b101010 7
0(
b100110 '
b100110 1
b100101 &
b100101 0
b100101 /
#1015
b101011 ,
b101010 +
1(
#1020
b101100 !
b101100 8
b101011 "
b101011 7
0(
b100111 '
b100111 1
b100110 &
b100110 0
b100110 /
#1025
b101100 ,
b101011 +
1(
#1030
b101101 !
b101101 8
b101100 "
b101100 7
0(
b101000 '
b101000 1
b100111 &
b100111 0
b100111 /
#1035
b101101 ,
b101100 +
1(
#1040
b101110 !
b101110 8
b101101 "
b101101 7
0(
b101001 '
b101001 1
b101000 &
b101000 0
b101000 /
#1045
b101110 ,
b101101 +
1(
#1050
b101111 !
b101111 8
b101110 "
b101110 7
0(
b101010 '
b101010 1
b101001 &
b101001 0
b101001 /
#1055
b101111 ,
b101110 +
1(
#1060
b110000 !
b110000 8
b101111 "
b101111 7
0(
b101011 '
b101011 1
b101010 &
b101010 0
b101010 /
#1065
b110000 ,
b101111 +
1(
#1070
b110001 !
b110001 8
b110000 "
b110000 7
0(
b101100 '
b101100 1
b101011 &
b101011 0
b101011 /
#1075
b110001 ,
b110000 +
1(
#1080
b110010 !
b110010 8
b110001 "
b110001 7
0(
b101101 '
b101101 1
b101100 &
b101100 0
b101100 /
#1085
b110010 ,
b110001 +
1(
#1090
b110011 !
b110011 8
b110010 "
b110010 7
0(
b101110 '
b101110 1
b101101 &
b101101 0
b101101 /
#1095
b110011 ,
b110010 +
1(
#1100
b110100 !
b110100 8
b110011 "
b110011 7
0(
b101111 '
b101111 1
b101110 &
b101110 0
b101110 /
#1105
b110100 ,
b110011 +
1(
#1110
b110101 !
b110101 8
b110100 "
b110100 7
0(
b110000 '
b110000 1
b101111 &
b101111 0
b101111 /
#1115
b110101 ,
b110100 +
1(
#1120
b110110 !
b110110 8
b110101 "
b110101 7
0(
b110001 '
b110001 1
b110000 &
b110000 0
b110000 /
#1125
b110110 ,
b110101 +
1(
#1130
b110111 !
b110111 8
b110110 "
b110110 7
0(
b110010 '
b110010 1
b110001 &
b110001 0
b110001 /
#1135
b110111 ,
b110110 +
1(
#1140
b111000 !
b111000 8
b110111 "
b110111 7
0(
b110011 '
b110011 1
b110010 &
b110010 0
b110010 /
#1145
b111000 ,
b110111 +
1(
#1150
b111001 !
b111001 8
b111000 "
b111000 7
0(
b110100 '
b110100 1
b110011 &
b110011 0
b110011 /
#1155
b111001 ,
b111000 +
1(
#1160
b111010 !
b111010 8
b111001 "
b111001 7
0(
b110101 '
b110101 1
b110100 &
b110100 0
b110100 /
#1165
b111010 ,
b111001 +
1(
#1170
b111011 !
b111011 8
b111010 "
b111010 7
0(
b110110 '
b110110 1
b110101 &
b110101 0
b110101 /
#1175
b111011 ,
b111010 +
1(
#1180
b111100 !
b111100 8
b111011 "
b111011 7
0(
b110111 '
b110111 1
b110110 &
b110110 0
b110110 /
#1185
b111100 ,
b111011 +
1(
#1190
b111101 !
b111101 8
b111100 "
b111100 7
0(
b111000 '
b111000 1
b110111 &
b110111 0
b110111 /
#1195
b111101 ,
b111100 +
1(
#1200
b111110 !
b111110 8
b111101 "
b111101 7
0(
b111001 '
b111001 1
b111000 &
b111000 0
b111000 /
#1205
b111110 ,
b111101 +
1(
#1210
b111111 !
b111111 8
b111110 "
b111110 7
0(
b111010 '
b111010 1
b111001 &
b111001 0
b111001 /
#1215
b111111 ,
b111110 +
1(
#1220
b1000000 !
b1000000 8
b111111 "
b111111 7
0(
b111011 '
b111011 1
b111010 &
b111010 0
b111010 /
#1225
b1000000 ,
b111111 +
1(
#1230
b1000001 !
b1000001 8
b1000000 "
b1000000 7
0(
b111100 '
b111100 1
b111011 &
b111011 0
b111011 /
#1235
b1000001 ,
b1000000 +
1(
#1240
b1000010 !
b1000010 8
b1000001 "
b1000001 7
0(
b111101 '
b111101 1
b111100 &
b111100 0
b111100 /
#1245
b1000010 ,
b1000001 +
1(
#1250
b1000011 !
b1000011 8
b1000010 "
b1000010 7
0(
b111110 '
b111110 1
b111101 &
b111101 0
b111101 /
#1255
b1000011 ,
b1000010 +
1(
#1260
b1000100 !
b1000100 8
b1000011 "
b1000011 7
0(
b111111 '
b111111 1
b111110 &
b111110 0
b111110 /
#1265
b1000100 ,
b1000011 +
1(
#1270
b1001001 !
b1001001 8
b1000100 "
b1000100 7
0(
b0 '
b0 1
b111111 &
b111111 0
b111111 /
#1275
bx ,
b1000100 +
1(
#1280
0(
b1000000 /
