06Assignments/function_task/function/rca/ripple_adder.v
:module rca;
reg [7:0]a,b;
wire [7:0]sum;
wire cout;
wire [6:0]c;
function [1:0]half_adder;
input x,y;
begin
half_adder[0] = x^y;
half_adder[1] = x&y;
end
endfunction

function [1:0]full_adder;
input x,y,cin;
begin
full_adder[1] = x^y^cin;
full_adder[0] = (x&y)|(y&cin)|(cin&x);
end
endfunction

wire [1:0] ha0;
wire [1:0] fa1,fa2,fa3,fa4,fa5,fa6,fa7;

assign ha0 = half_adder(a[0],b[0]);
assign sum[0] = ha0[0];
assign c[0]   = ha0[1];

assign fa1 = full_adder(a[1],b[1],c[0]);
assign sum[1] = fa1[0];
assign c[1]   = fa1[1];

assign fa2 = full_adder(a[2],b[2],c[1]);
assign sum[2] = fa2[0];
assign c[2]   = fa2[1];

assign fa3 = full_adder(a[3],b[3],c[2]);
assign sum[3] = fa3[0];
assign c[3]   = fa3[1];

assign fa4 = full_adder(a[4],b[4],c[3]);
assign sum[4] = fa4[0];
assign c[4]   = fa4[1];

assign fa5 = full_adder(a[5],b[5],c[4]);
assign sum[5] = fa5[0];
assign c[5]   = fa5[1];

assign fa6 = full_adder(a[6],b[6],c[5]);
assign sum[6] = fa6[0];
assign c[6]   = fa6[1];

assign fa7 = full_adder(a[7],b[7],c[6]);
assign sum[7] = fa7[0];
assign cout   = fa7[1];

integer i,j;
initial begin
$dumpfile("rca.vcd");
$dumpvars(0,rca);
$monitor("Time=%0t,a=%b,b=%b,sum=%b,cout=%b",$time,a,b,sum,cout);
for(i=0;i<16;i=i+1)
begin
for(j=0;j<16;j=j+1)
begin
a=i;
b=j;
#10;
end
end
end
endmodule

06Assignments/function_task/function/rca/rca.vcd
$date
	Wed Feb 18 12:02:20 2026
$end
$version
	Icarus Verilog
$end
$timescale
	1s
$end
$scope module rca $end
$var wire 8 ! sum [7:0] $end
$var wire 2 " ha0 [1:0] $end
$var wire 2 # fa7 [1:0] $end
$var wire 2 $ fa6 [1:0] $end
$var wire 2 % fa5 [1:0] $end
$var wire 2 & fa4 [1:0] $end
$var wire 2 ' fa3 [1:0] $end
$var wire 2 ( fa2 [1:0] $end
$var wire 2 ) fa1 [1:0] $end
$var wire 1 * cout $end
$var wire 7 + c [6:0] $end
$var reg 8 , a [7:0] $end
$var reg 8 - b [7:0] $end
$var integer 32 . i [31:0] $end
$var integer 32 / j [31:0] $end
$scope function full_adder $end
$var reg 1 0 cin $end
$var reg 1 1 x $end
$var reg 1 2 y $end
$upscope $end
$scope function half_adder $end
$var reg 1 3 x $end
$var reg 1 4 y $end
$upscope $end
$upscope $end
$enddefinitions $end
$comment Show the parameter values. $end
$dumpall
$end
#0
$dumpvars
04
03
02
01
00
b0 /
b0 .
b0 -
b0 ,
b0 +
0*
b0 )
b0 (
b0 '
b0 &
b0 %
b0 $
b0 #
b0 "
b0 !
$end
#10
b1 !
b1 "
14
b1 -
b1 /
#20
b10 !
b0 "
04
b1 )
12
b10 -
b10 /
#30
b11 !
b1 "
14
b11 -
b11 /
#40
b100 !
b0 "
04
b0 )
02
b1 (
b100 -
b100 /
#50
b101 !
b1 "
14
b101 -
b101 /
#60
b110 !
b0 "
04
b1 )
12
b110 -
b110 /
#70
b111 !
b1 "
14
b111 -
b111 /
#80
b1000 !
b0 "
04
b0 )
b0 (
02
b1 '
b1000 -
b1000 /
#90
b1001 !
b1 "
14
b1001 -
b1001 /
#100
b1010 !
b0 "
04
b1 )
12
b1010 -
b1010 /
#110
b1011 !
b1 "
14
b1011 -
b1011 /
#120
b1100 !
b0 "
04
b0 )
02
b1 (
b1100 -
b1100 /
#130
b1101 !
b1 "
14
b1101 -
b1101 /
#140
b1110 !
b0 "
04
b1 )
12
b1110 -
b1110 /
#150
b1111 !
b1 "
14
b1111 -
b1111 /
#160
b1 !
b0 )
b0 (
b0 '
02
04
13
b0 -
b1 ,
b1 .
b0 /
#170
b1 )
10
b10 !
b1 +
b10 "
14
b1 -
b1 /
#180
00
b0 (
b11 !
b0 +
b1 "
04
b1 )
02
b10 -
b10 /
#190
b1 (
b10 )
10
02
b100 !
b11 +
b10 "
14
b11 -
b11 /
#200
00
b0 '
b101 !
b0 +
b1 "
04
b0 )
b1 (
02
b100 -
b100 /
#210
b1 )
10
b110 !
b1 +
b10 "
14
b101 -
b101 /
#220
b0 '
00
b1 (
b111 !
b0 +
b1 "
04
b1 )
02
b110 -
b110 /
#230
b1 '
b10 (
b10 )
10
02
b1000 !
b111 +
b10 "
14
b111 -
b111 /
#240
00
b0 &
b1001 !
b0 +
b1 "
04
b0 )
b0 (
b1 '
02
b1000 -
b1000 /
#250
b1 )
10
b1010 !
b1 +
b10 "
14
b1001 -
b1001 /
#260
00
b0 (
b1011 !
b0 +
b1 "
04
b1 )
02
b1010 -
b1010 /
#270
b1 (
b10 )
10
02
b1100 !
b11 +
b10 "
14
b1011 -
b1011 /
#280
b0 &
00
b1 '
b1101 !
b0 +
b1 "
04
b0 )
b1 (
02
b1100 -
b1100 /
#290
b1 )
10
b1110 !
b1 +
b10 "
14
b1101 -
b1101 /
#300
b0 &
b1 '
00
b1 (
b1111 !
b0 +
b1 "
04
b1 )
02
b1110 -
b1110 /
#310
b1 &
b10 '
b10 (
b10 )
10
02
b10000 !
b1111 +
b10 "
14
b1111 -
b1111 /
#320
b0 &
b1 )
00
b10 !
b0 +
b0 (
b0 '
b0 "
04
03
01
b0 -
b10 ,
b10 .
b0 /
#330
b11 !
b1 "
14
b1 -
b1 /
#340
b1 (
10
b100 !
b10 +
b0 "
04
b10 )
02
01
b10 -
b10 /
#350
b101 !
b1 "
14
b11 -
b11 /
#360
b0 '
b110 !
b0 +
b0 "
04
b1 )
00
01
b1 (
02
b100 -
b100 /
#370
b111 !
b1 "
14
b101 -
b101 /
#380
b1 '
b10 (
10
b1000 !
b110 +
b0 "
04
b10 )
02
01
b110 -
b110 /
#390
b1001 !
b1 "
14
b111 -
b111 /
#400
b0 &
b1010 !
b0 +
b0 "
04
b1 )
00
01
b0 (
b1 '
02
b1000 -
b1000 /
#410
b1011 !
b1 "
14
b1001 -
b1001 /
#420
b1 (
10
b1100 !
b10 +
b0 "
04
b10 )
02
01
b1010 -
b1010 /
#430
b1101 !
b1 "
14
b1011 -
b1011 /
#440
b0 &
b1 '
b1110 !
b0 +
b0 "
04
b1 )
00
01
b1 (
02
b1100 -
b1100 /
#450
b1111 !
b1 "
14
b1101 -
b1101 /
#460
b1 &
b10 '
b10 (
10
b10000 !
b1110 +
b0 "
04
b10 )
02
01
b1110 -
b1110 /
#470
b10001 !
b1 "
14
b1111 -
b1111 /
#480
b0 &
b11 !
b0 +
b1 )
00
01
b0 (
b0 '
04
13
b0 -
b11 ,
b11 .
b0 /
#490
b1 (
b10 )
10
01
b100 !
b11 +
b10 "
14
b1 -
b1 /
#500
00
b10 +
b101 !
b1 "
04
b10 )
12
11
b10 -
b10 /
#510
b11 )
10
b110 !
b11 +
b10 "
14
b11 -
b11 /
#520
00
b0 '
b111 !
b0 +
b1 "
04
b1 )
02
b1 (
01
b100 -
b100 /
#530
b1 '
b10 (
02
b10 )
10
01
b1000 !
b111 +
b10 "
14
b101 -
b101 /
#540
00
b110 +
b1001 !
b1 "
04
b10 )
12
11
b110 -
b110 /
#550
b11 )
10
b1010 !
b111 +
b10 "
14
b111 -
b111 /
#560
00
b0 &
b1011 !
b0 +
b1 "
04
b1 )
b0 (
02
b1 '
01
b1000 -
b1000 /
#570
b1 (
b10 )
10
01
b1100 !
b11 +
b10 "
14
b1001 -
b1001 /
#580
00
b10 +
b1101 !
b1 "
04
b10 )
12
11
b1010 -
b1010 /
#590
b11 )
10
b1110 !
b11 +
b10 "
14
b1011 -
b1011 /
#600
b0 &
00
b1 '
b1111 !
b0 +
b1 "
04
b1 )
02
b1 (
01
b1100 -
b1100 /
#610
b1 &
b10 '
b10 (
02
b10 )
10
01
b10000 !
b1111 +
b10 "
14
b1101 -
b1101 /
#620
00
b1110 +
b10001 !
b1 "
04
b10 )
12
11
b1110 -
b1110 /
#630
b11 )
10
b10010 !
b1111 +
b10 "
14
b1111 -
b1111 /
#640
b0 &
b1 (
00
b100 !
b0 +
b0 '
b0 "
04
03
b0 )
01
02
b0 -
b100 ,
b100 .
b0 /
#650
b101 !
b1 "
14
b1 -
b1 /
#660
b110 !
b0 "
04
b1 )
12
b10 -
b10 /
#670
b111 !
b1 "
14
b11 -
b11 /
#680
b1 '
10
b1000 !
b100 +
b0 "
04
b0 )
02
b10 (
01
b100 -
b100 /
#690
b1001 !
b1 "
14
b101 -
b101 /
#700
b1010 !
b0 "
04
b1 )
00
12
b110 -
b110 /
#710
b1011 !
b1 "
14
b111 -
b111 /
#720
b0 &
b1100 !
b0 +
b0 "
04
b0 )
b1 (
02
01
b1 '
00
b1000 -
b1000 /
#730
b1101 !
b1 "
14
b1001 -
b1001 /
#740
b1110 !
b0 "
04
b1 )
12
b1010 -
b1010 /
#750
b1111 !
b1 "
14
b1011 -
b1011 /
#760
b1 &
b10 '
10
b10000 !
b1100 +
b0 "
04
b0 )
02
b10 (
01
b1100 -
b1100 /
#770
b10001 !
b1 "
14
b1101 -
b1101 /
#780
b10010 !
b0 "
04
b1 )
00
12
b1110 -
b1110 /
#790
b10011 !
b1 "
14
b1111 -
b1111 /
#800
b0 &
b101 !
b0 +
b0 )
b1 (
01
b0 '
00
02
04
13
b0 -
b101 ,
b101 .
b0 /
#810
b1 )
10
b110 !
b1 +
b10 "
14
b1 -
b1 /
#820
b0 '
00
b1 (
01
b111 !
b0 +
b1 "
04
b1 )
02
b10 -
b10 /
#830
b1 '
b10 (
01
b10 )
10
02
b1000 !
b111 +
b10 "
14
b11 -
b11 /
#840
00
b100 +
b1001 !
b1 "
04
b0 )
b10 (
02
01
b100 -
b100 /
#850
b1 )
10
b1010 !
b101 +
b10 "
14
b101 -
b101 /
#860
00
b10 (
11
b1011 !
b100 +
b1 "
04
b1 )
12
b110 -
b110 /
#870
b11 (
b10 )
10
11
b1100 !
b111 +
b10 "
14
b111 -
b111 /
#880
00
b0 &
b1101 !
b0 +
b1 "
04
b0 )
b1 (
02
b1 '
01
b1000 -
b1000 /
#890
b1 )
10
b1110 !
b1 +
b10 "
14
b1001 -
b1001 /
#900
b0 &
b1 '
00
b1 (
01
b1111 !
b0 +
b1 "
04
b1 )
02
b1010 -
b1010 /
#910
b1 &
b10 '
b10 (
01
b10 )
10
02
b10000 !
b1111 +
b10 "
14
b1011 -
b1011 /
#920
00
b1100 +
b10001 !
b1 "
04
b0 )
b10 (
02
01
b1100 -
b1100 /
#930
b1 )
10
b10010 !
b1101 +
b10 "
14
b1101 -
b1101 /
#940
00
b10 (
11
b10011 !
b1100 +
b1 "
04
b1 )
12
b1110 -
b1110 /
#950
b11 (
b10 )
10
11
b10100 !
b1111 +
b10 "
14
b1111 -
b1111 /
#960
b0 &
b1 )
00
b110 !
b0 +
b1 (
b0 '
01
b0 "
04
03
02
b0 -
b110 ,
b110 .
b0 /
#970
b111 !
b1 "
14
b1 -
b1 /
#980
b1 '
b10 (
10
b1000 !
b110 +
b0 "
04
b10 )
02
01
b10 -
b10 /
#990
b1001 !
b1 "
14
b11 -
b11 /
#1000
b100 +
b1010 !
b0 "
04
b1 )
00
b10 (
12
11
b100 -
b100 /
#1010
b1011 !
b1 "
14
b101 -
b101 /
#1020
b11 (
10
b1100 !
b110 +
b0 "
04
b10 )
b110 -
b110 /
#1030
b1101 !
b1 "
14
b111 -
b111 /
#1040
b0 &
b1110 !
b0 +
b0 "
04
b1 )
00
b1 (
02
b1 '
01
b1000 -
b1000 /
#1050
b1111 !
b1 "
14
b1001 -
b1001 /
#1060
b1 &
b10 '
b10 (
10
b10000 !
b1110 +
b0 "
04
b10 )
02
01
b1010 -
b1010 /
#1070
b10001 !
b1 "
14
b1011 -
b1011 /
#1080
b1100 +
b10010 !
b0 "
04
b1 )
00
b10 (
12
11
b1100 -
b1100 /
#1090
b10011 !
b1 "
14
b1101 -
b1101 /
#1100
b11 (
10
b10100 !
b1110 +
b0 "
04
b10 )
b1110 -
b1110 /
#1110
b10101 !
b1 "
14
b1111 -
b1111 /
#1120
b0 &
b111 !
b0 +
b1 )
00
b1 (
b0 '
02
01
04
13
b0 -
b111 ,
b111 .
b0 /
#1130
b1 '
b10 (
b10 )
10
01
b1000 !
b111 +
b10 "
14
b1 -
b1 /
#1140
00
b110 +
b1001 !
b1 "
04
b10 )
12
11
b10 -
b10 /
#1150
b11 )
10
b1010 !
b111 +
b10 "
14
b11 -
b11 /
#1160
00
b100 +
b1011 !
b1 "
04
b1 )
12
b10 (
b100 -
b100 /
#1170
b11 (
b10 )
10
12
b1100 !
b111 +
b10 "
14
b101 -
b101 /
#1180
00
b110 +
b1101 !
b1 "
04
b10 )
b110 -
b110 /
#1190
b11 )
10
b1110 !
b111 +
b10 "
14
b111 -
b111 /
#1200
00
b0 &
b1111 !
b0 +
b1 "
04
b1 )
b1 (
02
b1 '
01
b1000 -
b1000 /
#1210
b1 &
b10 '
02
b10 (
b10 )
10
01
b10000 !
b1111 +
b10 "
14
b1001 -
b1001 /
#1220
00
b1110 +
b10001 !
b1 "
04
b10 )
12
11
b1010 -
b1010 /
#1230
b11 )
10
b10010 !
b1111 +
b10 "
14
b1011 -
b1011 /
#1240
00
b1100 +
b10011 !
b1 "
04
b1 )
12
b10 (
b1100 -
b1100 /
#1250
b11 (
b10 )
10
12
b10100 !
b1111 +
b10 "
14
b1101 -
b1101 /
#1260
00
b1110 +
b10101 !
b1 "
04
b10 )
b1110 -
b1110 /
#1270
b11 )
10
b10110 !
b1111 +
b10 "
14
b1111 -
b1111 /
#1280
b0 &
b1000 !
b1 '
00
b0 +
b0 "
04
03
b0 )
b0 (
01
02
b0 -
b1000 ,
b1000 .
b0 /
#1290
b1001 !
b1 "
14
b1 -
b1 /
#1300
b1010 !
b0 "
04
b1 )
12
b10 -
b10 /
#1310
b1011 !
b1 "
14
b11 -
b11 /
#1320
b1100 !
b0 "
04
b0 )
02
b1 (
b100 -
b100 /
#1330
b1101 !
b1 "
14
b101 -
b101 /
#1340
b1110 !
b0 "
04
b1 )
12
b110 -
b110 /
#1350
b1111 !
b1 "
14
b111 -
b111 /
#1360
b1 &
10
b10000 !
b1000 +
b0 "
04
b0 )
b0 (
02
b10 '
01
b1000 -
b1000 /
#1370
b10001 !
b1 "
14
b1001 -
b1001 /
#1380
b10010 !
b0 "
04
b1 )
00
12
b1010 -
b1010 /
#1390
b10011 !
b1 "
14
b1011 -
b1011 /
#1400
b10100 !
b0 "
04
b0 )
02
b1 (
b1100 -
b1100 /
#1410
b10101 !
b1 "
14
b1101 -
b1101 /
#1420
b10110 !
b0 "
04
b1 )
12
b1110 -
b1110 /
#1430
b10111 !
b1 "
14
b1111 -
b1111 /
#1440
b0 &
b1001 !
b0 +
b0 )
b0 (
b1 '
02
01
04
13
b0 -
b1001 ,
b1001 .
b0 /
#1450
b1 )
10
b1010 !
b1 +
b10 "
14
b1 -
b1 /
#1460
00
b0 (
b1011 !
b0 +
b1 "
04
b1 )
02
b10 -
b10 /
#1470
b1 (
b10 )
10
02
b1100 !
b11 +
b10 "
14
b11 -
b11 /
#1480
b0 &
00
b1 '
01
b1101 !
b0 +
b1 "
04
b0 )
b1 (
02
b100 -
b100 /
#1490
b1 )
10
b1110 !
b1 +
b10 "
14
b101 -
b101 /
#1500
b0 &
b1 '
01
00
b1 (
b1111 !
b0 +
b1 "
04
b1 )
02
b110 -
b110 /
#1510
b1 &
b10 '
01
b10 (
b10 )
10
02
b10000 !
b1111 +
b10 "
14
b111 -
b111 /
#1520
00
b1000 +
b10001 !
b1 "
04
b0 )
b0 (
b10 '
02
01
b1000 -
b1000 /
#1530
b1 )
10
b10010 !
b1001 +
b10 "
14
b1001 -
b1001 /
#1540
00
b0 (
b10011 !
b1000 +
b1 "
04
b1 )
02
b1010 -
b1010 /
#1550
b1 (
b10 )
10
02
b10100 !
b1011 +
b10 "
14
b1011 -
b1011 /
#1560
00
b10 '
11
b10101 !
b1000 +
b1 "
04
b0 )
b1 (
12
b1100 -
b1100 /
#1570
b1 )
10
02
01
b10110 !
b1001 +
b10 "
14
b1101 -
b1101 /
#1580
b10 '
11
00
b1 (
b10111 !
b1000 +
b1 "
04
b1 )
12
b1110 -
b1110 /
#1590
b11 '
b10 (
b10 )
10
11
b11000 !
b1111 +
b10 "
14
b1111 -
b1111 /
#1600
b0 &
b1 )
00
b1010 !
b0 +
b0 (
01
b1 '
b0 "
04
03
02
b0 -
b1010 ,
b1010 .
b0 /
#1610
b1011 !
b1 "
14
b1 -
b1 /
#1620
b1 (
10
b1100 !
b10 +
b0 "
04
b10 )
02
01
b10 -
b10 /
#1630
b1101 !
b1 "
14
b11 -
b11 /
#1640
b0 &
b1 '
b1110 !
b0 +
b0 "
04
b1 )
00
01
b1 (
02
b100 -
b100 /
#1650
b1111 !
b1 "
14
b101 -
b101 /
#1660
b1 &
b10 '
b10 (
10
b10000 !
b1110 +
b0 "
04
b10 )
02
01
b110 -
b110 /
#1670
b10001 !
b1 "
14
b111 -
b111 /
#1680
b1000 +
b10010 !
b0 "
04
b1 )
00
b0 (
b10 '
02
01
b1000 -
b1000 /
#1690
b10011 !
b1 "
14
b1001 -
b1001 /
#1700
b1 (
10
b10100 !
b1010 +
b0 "
04
b10 )
02
01
b1010 -
b1010 /
#1710
b10101 !
b1 "
14
b1011 -
b1011 /
#1720
b10 '
b10110 !
b1000 +
b0 "
04
b1 )
00
11
b1 (
12
b1100 -
b1100 /
#1730
b10111 !
b1 "
14
b1101 -
b1101 /
#1740
b11 '
b10 (
10
11
b11000 !
b1110 +
b0 "
04
b10 )
b1110 -
b1110 /
#1750
b11001 !
b1 "
14
b1111 -
b1111 /
#1760
b0 &
b0 +
b1011 !
b1 )
00
b0 (
01
b1 '
02
04
13
b0 -
b1011 ,
b1011 .
b0 /
#1770
b1 (
b10 )
10
01
b1100 !
b11 +
b10 "
14
b1 -
b1 /
#1780
00
b10 +
b1101 !
b1 "
04
b10 )
12
11
b10 -
b10 /
#1790
b11 )
10
b1110 !
b11 +
b10 "
14
b11 -
b11 /
#1800
b0 &
00
b1 '
b1111 !
b0 +
b1 "
04
b1 )
02
b1 (
01
b100 -
b100 /
#1810
b1 &
b10 '
b10 (
02
b10 )
10
01
b10000 !
b1111 +
b10 "
14
b101 -
b101 /
#1820
00
b1110 +
b10001 !
b1 "
04
b10 )
12
11
b110 -
b110 /
#1830
b11 )
10
b10010 !
b1111 +
b10 "
14
b111 -
b111 /
#1840
00
b1000 +
b10011 !
b1 "
04
b1 )
b0 (
02
01
b10 '
b1000 -
b1000 /
#1850
b1 (
b10 )
10
01
b10100 !
b1011 +
b10 "
14
b1001 -
b1001 /
#1860
00
b1010 +
b10101 !
b1 "
04
b10 )
12
11
b1010 -
b1010 /
#1870
b11 )
10
b10110 !
b1011 +
b10 "
14
b1011 -
b1011 /
#1880
00
b10 '
b10111 !
b1000 +
b1 "
04
b1 )
12
b1 (
11
b1100 -
b1100 /
#1890
b11 '
b10 (
11
b10 )
10
12
b11000 !
b1111 +
b10 "
14
b1101 -
b1101 /
#1900
00
b1110 +
b11001 !
b1 "
04
b10 )
b1110 -
b1110 /
#1910
b11 )
10
b11010 !
b1111 +
b10 "
14
b1111 -
b1111 /
#1920
b0 &
b1 (
00
b1100 !
b0 +
b1 '
b0 "
04
03
b0 )
01
02
b0 -
b1100 ,
b1100 .
b0 /
#1930
b1101 !
b1 "
14
b1 -
b1 /
#1940
b1110 !
b0 "
04
b1 )
12
b10 -
b10 /
#1950
b1111 !
b1 "
14
b11 -
b11 /
#1960
b1 &
b10 '
10
b10000 !
b1100 +
b0 "
04
b0 )
02
b10 (
01
b100 -
b100 /
#1970
b10001 !
b1 "
14
b101 -
b101 /
#1980
b10010 !
b0 "
04
b1 )
00
12
b110 -
b110 /
#1990
b10011 !
b1 "
14
b111 -
b111 /
#2000
b1000 +
b10100 !
b0 "
04
b0 )
b1 (
12
b10 '
00
11
b1000 -
b1000 /
#2010
b10101 !
b1 "
14
b1001 -
b1001 /
#2020
b10110 !
b0 "
04
b1 )
01
b1010 -
b1010 /
#2030
b10111 !
b1 "
14
b1011 -
b1011 /
#2040
b11 '
10
b11000 !
b1100 +
b0 "
04
b0 )
12
b10 (
11
b1100 -
b1100 /
#2050
b11001 !
b1 "
14
b1101 -
b1101 /
#2060
b11010 !
b0 "
04
b1 )
00
01
b1110 -
b1110 /
#2070
b11011 !
b1 "
14
b1111 -
b1111 /
#2080
b0 &
b0 +
b1101 !
b0 )
b1 (
b1 '
00
02
01
04
13
b0 -
b1101 ,
b1101 .
b0 /
#2090
b1 )
10
b1110 !
b1 +
b10 "
14
b1 -
b1 /
#2100
b0 &
b1 '
00
b1 (
01
b1111 !
b0 +
b1 "
04
b1 )
02
b10 -
b10 /
#2110
b1 &
b10 '
b10 (
01
b10 )
10
02
b10000 !
b1111 +
b10 "
14
b11 -
b11 /
#2120
00
b1100 +
b10001 !
b1 "
04
b0 )
b10 (
02
01
b100 -
b100 /
#2130
b1 )
10
b10010 !
b1101 +
b10 "
14
b101 -
b101 /
#2140
00
b10 (
11
b10011 !
b1100 +
b1 "
04
b1 )
12
b110 -
b110 /
#2150
b11 (
b10 )
10
11
b10100 !
b1111 +
b10 "
14
b111 -
b111 /
#2160
00
b1000 +
b10101 !
b1 "
04
b0 )
11
b1 (
12
b10 '
b1000 -
b1000 /
#2170
b1 )
10
02
01
b10110 !
b1001 +
b10 "
14
b1001 -
b1001 /
#2180
b10 '
00
b1 (
11
b10111 !
b1000 +
b1 "
04
b1 )
12
b1010 -
b1010 /
#2190
b11 '
b10 (
12
b10 )
10
11
b11000 !
b1111 +
b10 "
14
b1011 -
b1011 /
#2200
00
b1100 +
b11001 !
b1 "
04
b0 )
02
01
b10 (
b1100 -
b1100 /
#2210
b1 )
10
b11010 !
b1101 +
b10 "
14
b1101 -
b1101 /
#2220
00
b10 (
11
b11011 !
b1100 +
b1 "
04
b1 )
12
b1110 -
b1110 /
#2230
b11 (
b10 )
10
11
b11100 !
b1111 +
b10 "
14
b1111 -
b1111 /
#2240
b0 &
01
b1 )
00
b1110 !
b0 +
b1 (
b1 '
b0 "
04
03
02
b0 -
b1110 ,
b1110 .
b0 /
#2250
b1111 !
b1 "
14
b1 -
b1 /
#2260
b1 &
b10 '
b10 (
10
b10000 !
b1110 +
b0 "
04
b10 )
02
01
b10 -
b10 /
#2270
b10001 !
b1 "
14
b11 -
b11 /
#2280
b1100 +
b10010 !
b0 "
04
b1 )
00
b10 (
12
11
b100 -
b100 /
#2290
b10011 !
b1 "
14
b101 -
b101 /
#2300
b11 (
10
b10100 !
b1110 +
b0 "
04
b10 )
b110 -
b110 /
#2310
b10101 !
b1 "
14
b111 -
b111 /
#2320
b1000 +
b10110 !
b0 "
04
b1 )
00
b1 (
12
b10 '
b1000 -
b1000 /
#2330
b10111 !
b1 "
14
b1001 -
b1001 /
#2340
b11 '
b10 (
10
12
b11000 !
b1110 +
b0 "
04
b10 )
b1010 -
b1010 /
#2350
b11001 !
b1 "
14
b1011 -
b1011 /
#2360
b1100 +
b11010 !
b0 "
04
b1 )
00
12
b10 (
b1100 -
b1100 /
#2370
b11011 !
b1 "
14
b1101 -
b1101 /
#2380
b11 (
10
b11100 !
b1110 +
b0 "
04
b10 )
b1110 -
b1110 /
#2390
b11101 !
b1 "
14
b1111 -
b1111 /
#2400
b0 &
01
b0 +
b1111 !
b1 )
00
b1 (
b1 '
02
04
13
b0 -
b1111 ,
b1111 .
b0 /
#2410
b1 &
b10 '
b10 (
b10 )
10
01
b10000 !
b1111 +
b10 "
14
b1 -
b1 /
#2420
00
b1110 +
b10001 !
b1 "
04
b10 )
12
11
b10 -
b10 /
#2430
b11 )
10
b10010 !
b1111 +
b10 "
14
b11 -
b11 /
#2440
00
b1100 +
b10011 !
b1 "
04
b1 )
12
b10 (
b100 -
b100 /
#2450
b11 (
b10 )
10
12
b10100 !
b1111 +
b10 "
14
b101 -
b101 /
#2460
00
b1110 +
b10101 !
b1 "
04
b10 )
b110 -
b110 /
#2470
b11 )
10
b10110 !
b1111 +
b10 "
14
b111 -
b111 /
#2480
00
b1000 +
b10111 !
b1 "
04
b1 )
b1 (
12
b10 '
b1000 -
b1000 /
#2490
b11 '
b10 (
b10 )
10
12
b11000 !
b1111 +
b10 "
14
b1001 -
b1001 /
#2500
00
b1110 +
b11001 !
b1 "
04
b10 )
b1010 -
b1010 /
#2510
b11 )
10
b11010 !
b1111 +
b10 "
14
b1011 -
b1011 /
#2520
00
b1100 +
b11011 !
b1 "
04
b1 )
12
b10 (
b1100 -
b1100 /
#2530
b11 (
b10 )
10
12
b11100 !
b1111 +
b10 "
14
b1101 -
b1101 /
#2540
00
b1110 +
b11101 !
b1 "
04
b10 )
b1110 -
b1110 /
#2550
b11 )
10
b11110 !
b1111 +
b10 "
14
b1111 -
b1111 /
#2560
b10000 .
b10000 /
