10memory/syn/asyn/asyn_ram.v
module ram #(parameter width= 8 , address= 6, depth = 64)(
input clk,
input [width-1:0]data,
input wr_en,
input [address-1:0]addr,
output reg [width-1:0]q);
reg [width-1:0] mem[depth-1:0];

always @(posedge clk )
begin
if(wr_en)
mem[addr] <= data;
end
 
always @(*)
begin
	q <= mem[addr];
end

endmodule

10memory/syn/asyn/tb.v
module tb;
parameter width=8,depth=64,address=6;
reg [width-1:0]data;
reg [address-1:0]addr;
reg wr_en;
reg  clk;
wire [width-1:0]q;

ram #( .width(width),
	.depth(depth),
	.address(address))uut (
.data(data),
.addr(addr),
.wr_en(wr_en),
.clk(clk),
.q(q));
always #5 clk = ~clk;
integer i;
reg [width-1:0] golden[depth-1:0];

initial begin
clk=0;
wr_en=0;
data=0;
addr=0;

for(i=0;i<64;i=i+1)
begin
	wr_en=1;
	addr=i;
	data= i+5;
	golden[i] = i+5;
	#10;
end

for(i=0;i<64;i=i+1)
begin
	wr_en=0;
	addr=i;
	#10;

#100 $finish;
end
if(q==golden[i])
	$display("**Ram is working**|Time=%0t|clk=%b|wr_en=%d|data=%d|addr=%d|q=%d",$time,clk,wr_en,data,addr,q);
else
	$display("Ram is not working|Time=%0t|clk=%b|wr_en=%d|data=%d|addr=%d|q=%d",$time,clk,wr_en,data,addr,q);



end
initial begin
	$dumpfile("ram.vcd");
	$dumpvars(0,tb);
	$monitor("Time=%0t|clk=%b|data=%d|addr=%d|wr_en=%b|q=%d",$time,clk,data,addr,wr_en,q);
end
endmodule

10memory/single_port/asyn/ram.vcd
$date
	Fri Mar  6 20:09:19 2026
$end
$version
	Icarus Verilog
$end
$timescale
	1s
$end
$scope module tb $end
$var wire 8 ! q [7:0] $end
$var parameter 32 " address $end
$var parameter 32 # depth $end
$var parameter 32 $ width $end
$var reg 6 % addr [5:0] $end
$var reg 1 & clk $end
$var reg 8 ' data [7:0] $end
$var reg 1 ( wr_en $end
$var integer 32 ) i [31:0] $end
$scope module uut $end
$var wire 6 * addr [5:0] $end
$var wire 1 & clk $end
$var wire 8 + data [7:0] $end
$var wire 1 ( wr_en $end
$var parameter 32 , address $end
$var parameter 32 - depth $end
$var parameter 32 . width $end
$var reg 8 / q [7:0] $end
$upscope $end
$upscope $end
$enddefinitions $end
$comment Show the parameter values. $end
$dumpall
b1000 .
b1000000 -
b110 ,
b1000 $
b1000000 #
b110 "
$end
#0
$dumpvars
bx /
b101 +
b0 *
b0 )
1(
b101 '
0&
b0 %
bx !
$end
#5
b101 !
b101 /
1&
#10
bx !
bx /
0&
b110 '
b110 +
b1 %
b1 *
b1 )
#15
b110 !
b110 /
1&
#20
bx !
bx /
0&
b111 '
b111 +
b10 %
b10 *
b10 )
#25
b111 !
b111 /
1&
#30
bx !
bx /
0&
b1000 '
b1000 +
b11 %
b11 *
b11 )
#35
b1000 !
b1000 /
1&
#40
bx !
bx /
0&
b1001 '
b1001 +
b100 %
b100 *
b100 )
#45
b1001 !
b1001 /
1&
#50
bx !
bx /
0&
b1010 '
b1010 +
b101 %
b101 *
b101 )
#55
b1010 !
b1010 /
1&
#60
bx !
bx /
0&
b1011 '
b1011 +
b110 %
b110 *
b110 )
#65
b1011 !
b1011 /
1&
#70
bx !
bx /
0&
b1100 '
b1100 +
b111 %
b111 *
b111 )
#75
b1100 !
b1100 /
1&
#80
bx !
bx /
0&
b1101 '
b1101 +
b1000 %
b1000 *
b1000 )
#85
b1101 !
b1101 /
1&
#90
bx !
bx /
0&
b1110 '
b1110 +
b1001 %
b1001 *
b1001 )
#95
b1110 !
b1110 /
1&
#100
bx !
bx /
0&
b1111 '
b1111 +
b1010 %
b1010 *
b1010 )
#105
b1111 !
b1111 /
1&
#110
bx !
bx /
0&
b10000 '
b10000 +
b1011 %
b1011 *
b1011 )
#115
b10000 !
b10000 /
1&
#120
bx !
bx /
0&
b10001 '
b10001 +
b1100 %
b1100 *
b1100 )
#125
b10001 !
b10001 /
1&
#130
bx !
bx /
0&
b10010 '
b10010 +
b1101 %
b1101 *
b1101 )
#135
b10010 !
b10010 /
1&
#140
bx !
bx /
0&
b10011 '
b10011 +
b1110 %
b1110 *
b1110 )
#145
b10011 !
b10011 /
1&
#150
bx !
bx /
0&
b10100 '
b10100 +
b1111 %
b1111 *
b1111 )
#155
b10100 !
b10100 /
1&
#160
bx !
bx /
0&
b10101 '
b10101 +
b10000 %
b10000 *
b10000 )
#165
b10101 !
b10101 /
1&
#170
bx !
bx /
0&
b10110 '
b10110 +
b10001 %
b10001 *
b10001 )
#175
b10110 !
b10110 /
1&
#180
bx !
bx /
0&
b10111 '
b10111 +
b10010 %
b10010 *
b10010 )
#185
b10111 !
b10111 /
1&
#190
bx !
bx /
0&
b11000 '
b11000 +
b10011 %
b10011 *
b10011 )
#195
b11000 !
b11000 /
1&
#200
bx !
bx /
0&
b11001 '
b11001 +
b10100 %
b10100 *
b10100 )
#205
b11001 !
b11001 /
1&
#210
bx !
bx /
0&
b11010 '
b11010 +
b10101 %
b10101 *
b10101 )
#215
b11010 !
b11010 /
1&
#220
bx !
bx /
0&
b11011 '
b11011 +
b10110 %
b10110 *
b10110 )
#225
b11011 !
b11011 /
1&
#230
bx !
bx /
0&
b11100 '
b11100 +
b10111 %
b10111 *
b10111 )
#235
b11100 !
b11100 /
1&
#240
bx !
bx /
0&
b11101 '
b11101 +
b11000 %
b11000 *
b11000 )
#245
b11101 !
b11101 /
1&
#250
bx !
bx /
0&
b11110 '
b11110 +
b11001 %
b11001 *
b11001 )
#255
b11110 !
b11110 /
1&
#260
bx !
bx /
0&
b11111 '
b11111 +
b11010 %
b11010 *
b11010 )
#265
b11111 !
b11111 /
1&
#270
bx !
bx /
0&
b100000 '
b100000 +
b11011 %
b11011 *
b11011 )
#275
b100000 !
b100000 /
1&
#280
bx !
bx /
0&
b100001 '
b100001 +
b11100 %
b11100 *
b11100 )
#285
b100001 !
b100001 /
1&
#290
bx !
bx /
0&
b100010 '
b100010 +
b11101 %
b11101 *
b11101 )
#295
b100010 !
b100010 /
1&
#300
bx !
bx /
0&
b100011 '
b100011 +
b11110 %
b11110 *
b11110 )
#305
b100011 !
b100011 /
1&
#310
bx !
bx /
0&
b100100 '
b100100 +
b11111 %
b11111 *
b11111 )
#315
b100100 !
b100100 /
1&
#320
bx !
bx /
0&
b100101 '
b100101 +
b100000 %
b100000 *
b100000 )
#325
b100101 !
b100101 /
1&
#330
bx !
bx /
0&
b100110 '
b100110 +
b100001 %
b100001 *
b100001 )
#335
b100110 !
b100110 /
1&
#340
bx !
bx /
0&
b100111 '
b100111 +
b100010 %
b100010 *
b100010 )
#345
b100111 !
b100111 /
1&
#350
bx !
bx /
0&
b101000 '
b101000 +
b100011 %
b100011 *
b100011 )
#355
b101000 !
b101000 /
1&
#360
bx !
bx /
0&
b101001 '
b101001 +
b100100 %
b100100 *
b100100 )
#365
b101001 !
b101001 /
1&
#370
bx !
bx /
0&
b101010 '
b101010 +
b100101 %
b100101 *
b100101 )
#375
b101010 !
b101010 /
1&
#380
bx !
bx /
0&
b101011 '
b101011 +
b100110 %
b100110 *
b100110 )
#385
b101011 !
b101011 /
1&
#390
bx !
bx /
0&
b101100 '
b101100 +
b100111 %
b100111 *
b100111 )
#395
b101100 !
b101100 /
1&
#400
bx !
bx /
0&
b101101 '
b101101 +
b101000 %
b101000 *
b101000 )
#405
b101101 !
b101101 /
1&
#410
bx !
bx /
0&
b101110 '
b101110 +
b101001 %
b101001 *
b101001 )
#415
b101110 !
b101110 /
1&
#420
bx !
bx /
0&
b101111 '
b101111 +
b101010 %
b101010 *
b101010 )
#425
b101111 !
b101111 /
1&
#430
bx !
bx /
0&
b110000 '
b110000 +
b101011 %
b101011 *
b101011 )
#435
b110000 !
b110000 /
1&
#440
bx !
bx /
0&
b110001 '
b110001 +
b101100 %
b101100 *
b101100 )
#445
b110001 !
b110001 /
1&
#450
bx !
bx /
0&
b110010 '
b110010 +
b101101 %
b101101 *
b101101 )
#455
b110010 !
b110010 /
1&
#460
bx !
bx /
0&
b110011 '
b110011 +
b101110 %
b101110 *
b101110 )
#465
b110011 !
b110011 /
1&
#470
bx !
bx /
0&
b110100 '
b110100 +
b101111 %
b101111 *
b101111 )
#475
b110100 !
b110100 /
1&
#480
bx !
bx /
0&
b110101 '
b110101 +
b110000 %
b110000 *
b110000 )
#485
b110101 !
b110101 /
1&
#490
bx !
bx /
0&
b110110 '
b110110 +
b110001 %
b110001 *
b110001 )
#495
b110110 !
b110110 /
1&
#500
bx !
bx /
0&
b110111 '
b110111 +
b110010 %
b110010 *
b110010 )
#505
b110111 !
b110111 /
1&
#510
bx !
bx /
0&
b111000 '
b111000 +
b110011 %
b110011 *
b110011 )
#515
b111000 !
b111000 /
1&
#520
bx !
bx /
0&
b111001 '
b111001 +
b110100 %
b110100 *
b110100 )
#525
b111001 !
b111001 /
1&
#530
bx !
bx /
0&
b111010 '
b111010 +
b110101 %
b110101 *
b110101 )
#535
b111010 !
b111010 /
1&
#540
bx !
bx /
0&
b111011 '
b111011 +
b110110 %
b110110 *
b110110 )
#545
b111011 !
b111011 /
1&
#550
bx !
bx /
0&
b111100 '
b111100 +
b110111 %
b110111 *
b110111 )
#555
b111100 !
b111100 /
1&
#560
bx !
bx /
0&
b111101 '
b111101 +
b111000 %
b111000 *
b111000 )
#565
b111101 !
b111101 /
1&
#570
bx !
bx /
0&
b111110 '
b111110 +
b111001 %
b111001 *
b111001 )
#575
b111110 !
b111110 /
1&
#580
bx !
bx /
0&
b111111 '
b111111 +
b111010 %
b111010 *
b111010 )
#585
b111111 !
b111111 /
1&
#590
bx !
bx /
0&
b1000000 '
b1000000 +
b111011 %
b111011 *
b111011 )
#595
b1000000 !
b1000000 /
1&
#600
bx !
bx /
0&
b1000001 '
b1000001 +
b111100 %
b111100 *
b111100 )
#605
b1000001 !
b1000001 /
1&
#610
bx !
bx /
0&
b1000010 '
b1000010 +
b111101 %
b111101 *
b111101 )
#615
b1000010 !
b1000010 /
1&
#620
bx !
bx /
0&
b1000011 '
b1000011 +
b111110 %
b111110 *
b111110 )
#625
b1000011 !
b1000011 /
1&
#630
bx !
bx /
0&
b1000100 '
b1000100 +
b111111 %
b111111 *
b111111 )
#635
b1000100 !
b1000100 /
1&
#640
b101 !
b101 /
0&
b0 %
b0 *
0(
b0 )
