10memory/syn/asyn/asyn_ram.v
module ram #(parameter width= 8 , address= 6, depth = 64)(
input clk,
input [width-1:0]data,
input wr_en,
input [address-1:0]addr,
output reg [width-1:0]q);
reg [width-1:0] mem[depth-1:0];

always @(posedge clk )
begin
if(wr_en)
mem[addr] <= data;
end
 
always @(*)
begin
	q <= mem[addr];
end

endmodule

10memory/single_port/syn/tb.v
module tb;
reg [7:0]data;
reg [5:0]addr;
reg wr_en;
reg  clk;
wire [7:0]q;

ram uut(
.data(data),
.addr(addr),
.wr_en(wr_en),
.clk(clk),
.q(q));
always #5 clk = ~clk;
initial begin
clk=0;data=8'b00100010;addr=6'b101010;wr_en=1;#10;
data=8'b00100010;addr=6'b101000;wr_en=1;#10;
data=8'b10100010;addr=6'b001010;wr_en=1;#10;
data=8'b01100010;addr=6'b101011;wr_en=1;#10;
data=8'b00101110;addr=6'b101011;wr_en=0;#10;
data=8'b00111110;addr=6'b001010;wr_en=0;#10;
data=8'b00000010;addr=6'b101011;wr_en=0;#10;
data=8'b10000010;addr=6'b101011;wr_en=1;#10;
data=8'b10000010;addr=6'b101011;wr_en=0;#10;

$finish;
end
initial begin
	$dumpfile("ram.vcd");
	$dumpvars(0,tb);
	$monitor("Time=%0t|clk=%b|data=%d|addr=%d|wr_en=%b|q=%d",$time,clk,data,addr,wr_en,q);
end
endmodule

10memory/syn/ram.vcd
$date
	Fri Mar  6 22:36:21 2026
$end
$version
	Icarus Verilog
$end
$timescale
	1s
$end
$scope module tb $end
$var wire 8 ! q [7:0] $end
$var reg 6 " addr [5:0] $end
$var reg 1 # clk $end
$var reg 8 $ data [7:0] $end
$var reg 1 % wr_en $end
$scope module uut $end
$var wire 6 & addr [5:0] $end
$var wire 1 # clk $end
$var wire 8 ' data [7:0] $end
$var wire 1 % wr_en $end
$var reg 8 ( q [7:0] $end
$upscope $end
$upscope $end
$enddefinitions $end
$comment Show the parameter values. $end
$dumpall
$end
#0
$dumpvars
bx (
b100010 '
b101010 &
1%
b100010 $
0#
b101010 "
bx !
$end
#5
b0 !
b0 (
1#
#10
0#
b101000 "
b101000 &
#15
1#
#20
0#
b1010 "
b1010 &
b10100010 $
b10100010 '
#25
1#
#30
0#
b101011 "
b101011 &
b1100010 $
b1100010 '
#35
1#
#40
0#
0%
b101110 $
b101110 '
#45
b1100010 !
b1100010 (
1#
#50
0#
b1010 "
b1010 &
b111110 $
b111110 '
#55
b10100010 !
b10100010 (
1#
#60
0#
b101011 "
b101011 &
b10 $
b10 '
#65
b1100010 !
b1100010 (
1#
#70
0#
1%
b10000010 $
b10000010 '
#75
b0 !
b0 (
1#
#80
0#
0%
#85
b10000010 !
b10000010 (
1#
