03sequential_circuits/sr_flipflop/sr_using_t.v
module sr_ff(
	input s,r,clk,rst,
output reg q);
always @(posedge clk or posedge rst)
begin 
if(rst)
q<=1'b0;
else
case({s,r})
2'b00:q<=q;
2'b01:q<=1'b0;
2'b10:q<=1'b1;
2'b11:q<=1'bx;
endcase
end
endmodule


module t_ff(
input t,clk,rst,
output q);
assign d0= t&~q;
assign d1= t&q;
sr_ff sr1(
.s(d0),
.r(d1),
.clk(clk),
.rst(rst),
.q(q));
endmodule

03sequential_circuits/sr_flipflop/flipflop/tb_ff.v
module tb_ff;
reg s,r,clk,rst;
wire q;
sr_ff uut(
.s(s),
.r(r),
.clk(clk),
.rst(rst),
.q(q));
always #5 clk = ~clk;
initial begin
$dumpfile("flipflop.vcd");
$dumpvars(0,tb_ff);
$monitor("Time=%0t|clk=%b|rst=%b|s=%b|r=%b|q=%b",$time,clk,rst,s,r,q);
clk=0;rst=1;s=0;r=0;#10;
clk=1;rst=0;s=0;r=0;#10;
clk=1;rst=0;s=1;r=0;;#10;
clk=1;rst=0;s=0;r=1;#10;
clk=1;rst=0;s=1;r=1;#10;
$finish;
end
endmodule

03sequential_circuits/sr_flipflop/flipflop.vcd
$date
	Tue Feb 10 22:42:05 2026
$end
$version
	Icarus Verilog
$end
$timescale
	1s
$end
$scope module tb_ff $end
$var wire 1 ! q $end
$var reg 1 " clk $end
$var reg 1 # r $end
$var reg 1 $ rst $end
$var reg 1 % s $end
$scope module uut $end
$var wire 1 " clk $end
$var wire 1 # r $end
$var wire 1 $ rst $end
$var wire 1 % s $end
$var reg 1 ! q $end
$upscope $end
$upscope $end
$enddefinitions $end
$comment Show the parameter values. $end
$dumpall
$end
#0
$dumpvars
0%
1$
0#
0"
0!
$end
#5
1"
#10
0"
0$
#15
1"
#20
0"
1%
#25
1!
1"
#30
0"
1#
0%
#35
0!
1"
#40
0"
1%
#45
x!
1"
