06Assignments/assignment4/odd_parity/odd.v
module odd_parity(
input a,b,c,d,
output out);
function odd;
input w,x,y,z;
begin
odd = ~(w^x^y^z);
end
endfunction
assign out = odd(a,b,c,d);
endmodule

06Assignments/assignment4/odd_parity/tb_odd.v
module tb_odd;
reg a,b,c,d;
wire out;
odd_parity uut(
.a(a),
.b(b),
.c(c),
.d(d),
.out(out));
integer i;
initial begin
$dumpfile("odd.vcd");
$dumpvars(0,tb_odd);
$monitor("Time=%0t|a=%b|b=%b|c=%b|d=%d|out=%b",$time,a,b,c,d,out);
for(i=0;i<16;i=i+1)
begin
{a,b,c,d}=i;
#10;
end
end
endmodule

06Assignments/assignment4/odd_parity/odd.vcd
$date
	Tue Feb 17 10:26:06 2026
$end
$version
	Icarus Verilog
$end
$timescale
	1s
$end
$scope module tb_odd $end
$var wire 1 ! out $end
$var reg 1 " a $end
$var reg 1 # b $end
$var reg 1 $ c $end
$var reg 1 % d $end
$var integer 32 & i [31:0] $end
$scope module uut $end
$var wire 1 " a $end
$var wire 1 # b $end
$var wire 1 $ c $end
$var wire 1 % d $end
$var wire 1 ! out $end
$scope function odd $end
$var reg 1 ' w $end
$var reg 1 ( x $end
$var reg 1 ) y $end
$var reg 1 * z $end
$upscope $end
$upscope $end
$upscope $end
$enddefinitions $end
$comment Show the parameter values. $end
$dumpall
$end
#0
$dumpvars
0*
0)
0(
0'
b0 &
0%
0$
0#
0"
1!
$end
#10
0!
1*
1%
b1 &
#20
0*
1)
1$
0%
b10 &
#30
1!
1*
1%
b11 &
#40
0!
0*
0)
1(
1#
0$
0%
b100 &
#50
1!
1*
1%
b101 &
#60
0*
1)
1$
0%
b110 &
#70
0!
1*
1%
b111 &
#80
0*
0)
0(
1'
1"
0#
0$
0%
b1000 &
#90
1!
1*
1%
b1001 &
#100
0*
1)
1$
0%
b1010 &
#110
0!
1*
1%
b1011 &
#120
1!
0*
0)
1(
1#
0$
0%
b1100 &
#130
0!
1*
1%
b1101 &
#140
0*
1)
1$
0%
b1110 &
#150
1!
1*
1%
b1111 &
#160
b10000 &
