test/q9/moore_overlapping.v
module seq(
input clk,rst,a,
output reg out);
parameter [2:0]s0=3'b000,
          s1=3'b001,
          s2=3'b010,
          s3=3'b011,
          s4=3'b100,
          s5=3'b101;
reg [2:0]state,next_state;
always @(posedge clk  or posedge rst)
begin
if(rst)
state <= 1'b0;
else 
state <= next_state;
end

always @(*)
begin
next_state <= 3'b000;
out <= 1'b0;
case(state)
s0:
begin
if(a)
next_state <= s1;
else
next_state <= s0; 
end
s1:
begin
if(a)
next_state <= s1;
else
next_state <= s2;
end

s2:
begin
if(a)
next_state <= s3;
else
next_state <= s0;
end

s3:
begin
if(a)
next_state <= s4;
else
next_state <= s2;
end

s4:
begin
if(a)
next_state <= s1;
else
next_state <= s5;
end

s5:

begin
	out<=1'b1;
if(a)
next_state <= s3;
else
next_state <= s0;
end
endcase
end
endmodule

test/q9/tb_moore.v
module tb;
reg clk,rst,a;
wire out;
seq uut(
.clk(clk),
.rst(rst),
.a(a),
.out(out));
always #5 clk = ~clk;
initial begin
clk =0;rst=1;a=0;#10;
clk=0;rst =1;#10;
clk=1; rst=0;#10;
a=1;#10;
a=1;#10;
a=0;#10;
a=1;#10;
a=1;#10;
a=0;#10;
a=1;#10;
a=1;#10;
a=0;#100;
$finish;
end
initial begin
$dumpfile("seq.vcd");
$dumpvars(0,tb);
$monitor("Time=%0t|clk=%b|rst=%b|a=%b|out=%b",$time,clk,rst,a,out);
end
endmodule

test/q9/seq.vcd
$date
	Wed Mar  4 10:11:38 2026
$end
$version
	Icarus Verilog
$end
$timescale
	1s
$end
$scope module tb $end
$var wire 1 ! out $end
$var reg 1 " a $end
$var reg 1 # clk $end
$var reg 1 $ rst $end
$scope module uut $end
$var wire 1 " a $end
$var wire 1 # clk $end
$var wire 1 $ rst $end
$var parameter 3 % s0 $end
$var parameter 3 & s1 $end
$var parameter 3 ' s2 $end
$var parameter 3 ( s3 $end
$var parameter 3 ) s4 $end
$var parameter 3 * s5 $end
$var reg 3 + next_state [2:0] $end
$var reg 1 ! out $end
$var reg 3 , state [2:0] $end
$upscope $end
$upscope $end
$enddefinitions $end
$comment Show the parameter values. $end
$dumpall
b101 *
b100 )
b11 (
b10 '
b1 &
b0 %
$end
#0
$dumpvars
b0 ,
b0 +
1$
0#
0"
0!
$end
#5
1#
#10
1#
#15
0#
#20
0$
0#
#25
1#
#30
b1 +
0#
1"
#35
b1 +
b1 ,
1#
#40
0#
#45
1#
#50
b10 +
0#
0"
#55
b0 +
b10 ,
1#
#60
b11 +
0#
1"
#65
b100 +
b11 ,
1#
#70
0#
#75
b1 +
b100 ,
1#
#80
b101 +
0#
0"
#85
1!
b0 +
b101 ,
1#
#90
b11 +
1!
0#
1"
#95
0!
b100 +
b11 ,
1#
#100
0#
#105
b1 +
b100 ,
1#
#110
b101 +
0#
0"
#115
1!
b0 +
b101 ,
1#
#120
0#
#125
0!
b0 ,
1#
