06Assignments/assignment4/graycode/graycode.v
module graycode(
input [3:0]b,
output [3:0]g);
function [3:0]gray;
input [3:0]in;
begin
 gray[3]=in[3];
 gray[2]=in[3]^in[2];
 gray[1]=in[2]^in[1];
 gray[0]=in[1]^in[0];
end
endfunction
assign g= gray(b);
endmodule

06Assignments/assignment4/graycode/tb_gray.v
module tb_gray;
reg [3:0]b;
wire [3:0]g;
graycode uut(
.b(b),
.g(g));
integer i;
initial begin
$dumpfile("code.vcd");
$dumpvars(0,tb_gray);
$monitor("Time=%0t|b=%b|g=%b",$time,b,g);
for(i=0;i<16;i=i+1)
begin
b=i;#10;
end
#100 $finish;
end
endmodule

06Assignments/assignment4/graycode/code.vcd
$date
	Tue Feb 17 09:49:16 2026
$end
$version
	Icarus Verilog
$end
$timescale
	1s
$end
$scope module tb_gray $end
$var wire 4 ! g [3:0] $end
$var reg 4 " b [3:0] $end
$var integer 32 # i [31:0] $end
$scope module uut $end
$var wire 4 $ b [3:0] $end
$var wire 4 % g [3:0] $end
$scope function gray $end
$var reg 4 & in [3:0] $end
$upscope $end
$upscope $end
$upscope $end
$enddefinitions $end
$comment Show the parameter values. $end
$dumpall
$end
#0
$dumpvars
b0 &
b0 %
b0 $
b0 #
b0 "
b0 !
$end
#10
b1 !
b1 %
b1 &
b1 "
b1 $
b1 #
#20
b11 !
b11 %
b10 &
b10 "
b10 $
b10 #
#30
b10 !
b10 %
b11 &
b11 "
b11 $
b11 #
#40
b110 !
b110 %
b100 &
b100 "
b100 $
b100 #
#50
b111 !
b111 %
b101 &
b101 "
b101 $
b101 #
#60
b101 !
b101 %
b110 &
b110 "
b110 $
b110 #
#70
b100 !
b100 %
b111 &
b111 "
b111 $
b111 #
#80
b1100 !
b1100 %
b1000 &
b1000 "
b1000 $
b1000 #
#90
b1101 !
b1101 %
b1001 &
b1001 "
b1001 $
b1001 #
#100
b1111 !
b1111 %
b1010 &
b1010 "
b1010 $
b1010 #
#110
b1110 !
b1110 %
b1011 &
b1011 "
b1011 $
b1011 #
#120
b1010 !
b1010 %
b1100 &
b1100 "
b1100 $
b1100 #
#130
b1011 !
b1011 %
b1101 &
b1101 "
b1101 $
b1101 #
#140
b1001 !
b1001 %
b1110 &
b1110 "
b1110 $
b1110 #
#150
b1000 !
b1000 %
b1111 &
b1111 "
b1111 $
b1111 #
#160
b10000 #
