06Assignments/assignment4/min_8bits/min.v
module minimum(
input [7:0]a,b,
output [7:0]out);
function [7:0]min;
input [7:0]x,y;
begin
if(x>y)
min = y;
else
min = x;
end
endfunction
assign out = min(a,b);
endmodule

06Assignments/assignment4/min_8bits/tb_min.v
module tb_min;
reg [7:0]a,b;
wire [7:0]out;
minimum uut(
.a(a),
.b(b),
.out(out));
integer i,j;
initial begin
$dumpfile("min.vcd");
$dumpvars(0,tb_min);
$monitor("a=%b|b=%b|out=%b",a,b,out);
for(i=0;i<16;i=i+1)
begin
a=$urandom_range(256,0);
b=$urandom_range(256,0);
#10;
end
end
endmodule

06Assignments/assignment4/min_8bits/min.vcd
$date
	Thu Feb 19 13:20:56 2026
$end
$version
	Icarus Verilog
$end
$timescale
	1s
$end
$scope module tb_min $end
$var wire 8 ! out [7:0] $end
$var reg 8 " a [7:0] $end
$var reg 8 # b [7:0] $end
$var integer 32 $ i [31:0] $end
$scope module uut $end
$var wire 8 % a [7:0] $end
$var wire 8 & b [7:0] $end
$var wire 8 ' out [7:0] $end
$scope function min $end
$var reg 8 ( x [7:0] $end
$var reg 8 ) y [7:0] $end
$upscope $end
$upscope $end
$upscope $end
$enddefinitions $end
$comment Show the parameter values. $end
$dumpall
$end
#0
$dumpvars
b1000000 )
b10010010 (
b1000000 '
b1000000 &
b10010010 %
b0 $
b1000000 #
b10010010 "
b1000000 !
$end
#10
b100 !
b100 '
b110010 )
b100 (
b110010 #
b110010 &
b100 "
b100 %
b1 $
#20
b10000111 !
b10000111 '
b11000111 )
b10000111 (
b11000111 #
b11000111 &
b10000111 "
b10000111 %
b10 $
#30
b1001 !
b1001 '
b1001 )
b110010 (
b1001 #
b1001 &
b110010 "
b110010 %
b11 $
#40
b10000001 !
b10000001 '
b10000111 )
b10000001 (
b10000111 #
b10000111 &
b10000001 "
b10000001 %
b100 $
#50
b10011111 !
b10011111 '
b10011111 )
b10111011 (
b10011111 #
b10011111 &
b10111011 "
b10111011 %
b101 $
#60
b11000110 !
b11000110 '
b11000110 )
b11110111 (
b11000110 #
b11000110 &
b11110111 "
b11110111 %
b110 $
#70
b1100011 !
b1100011 '
b1100011 )
b11111101 (
b1100011 #
b1100011 &
b11111101 "
b11111101 %
b111 $
#80
b1010101 !
b1010101 '
b1010101 )
b1100011 (
b1010101 #
b1010101 &
b1100011 "
b1100011 %
b1000 $
#90
b111100 !
b111100 '
b111100 )
b11110011 (
b111100 #
b111100 &
b11110011 "
b11110011 %
b1001 $
#100
b1001 !
b1001 '
b11001000 )
b1001 (
b11001000 #
b11001000 &
b1001 "
b1001 %
b1010 $
#110
b1100111 !
b1100111 '
b1100111 )
b11111010 (
b1100111 #
b1100111 &
b11111010 "
b11111010 %
b1011 $
#120
b1100011 !
b1100011 '
b1100011 )
b1110100 (
b1100011 #
b1100011 &
b1110100 "
b1110100 %
b1100 $
#130
b1011110 !
b1011110 '
b1011110 )
b10101111 (
b1011110 #
b1011110 &
b10101111 "
b10101111 %
b1101 $
#140
b10110 !
b10110 '
b110010 )
b10110 (
b110010 #
b110010 &
b10110 "
b10110 %
b1110 $
#150
b110010 !
b110010 '
b10000101 )
b110010 (
b10000101 #
b10000101 &
b110010 "
b110010 %
b1111 $
#160
b10000 $
