05shift_register/piso.v
module piso(
input [3:0]in,
input clk,rst,load,
output reg out);
reg [3:0]shift;
always @(posedge clk or posedge rst)
begin
if(rst)
 shift <= 4'b0000;
else if(load)
 shift <= in;
else
begin
 shift <= ({shift[2:0],in});
 out <= shift[3];
end
end
endmodule

05shift_register/tb_piso.v
module tb_shiftreg;
reg clk,rst;
reg [3:0]in;
reg load;
wire  out;
piso uut(
.clk(clk),
.rst(rst),
.in(in),
.load(load),
.out(out));
always #5 clk = ~clk;
  initial begin
    $dumpfile("shiftreg.vcd");
    $dumpvars(0,tb_shiftreg);
    $monitor("Time=%0t,in=%b,rst=%b,load=%b|out=%b",$time,in,rst,load,out);
     clk=0;rst=1;load = 1;
    in=4'b0011;#10;
    in=4'b1010;#10;
    load=0;
    in=4'b1111;#10;
    in=4'b1011;#10;
    rst=0; #10;
     load =1;in=4'b1101;#10;
     load =0;in=4'b1100;#10;
    #200  $finish;
  end
endmodule

05shift_register/shiftreg.vcd
$date
	Wed Feb 18 16:20:45 2026
$end
$version
	Icarus Verilog
$end
$timescale
	1s
$end
$scope module tb_shiftreg $end
$var wire 1 ! out $end
$var reg 1 " clk $end
$var reg 4 # in [3:0] $end
$var reg 1 $ load $end
$var reg 1 % rst $end
$scope module uut $end
$var wire 1 " clk $end
$var wire 4 & in [3:0] $end
$var wire 1 $ load $end
$var wire 1 % rst $end
$var reg 1 ! out $end
$var reg 4 ' shift [3:0] $end
$upscope $end
$upscope $end
$enddefinitions $end
$comment Show the parameter values. $end
$dumpall
$end
#0
$dumpvars
b0 '
b11 &
1%
1$
b11 #
0"
x!
$end
#5
1"
#10
0"
b1010 #
b1010 &
#15
1"
#20
0"
b1111 #
b1111 &
0$
#25
1"
#30
0"
b1011 #
b1011 &
#35
1"
#40
0"
0%
#45
0!
b1011 '
1"
#50
0"
b1101 #
b1101 &
1$
#55
b1101 '
1"
#60
0"
b1100 #
b1100 &
0$
#65
1!
b1100 '
1"
