04finite_state_machine/fsm_101/moore_nonoverlapping.v
module fsm(
input a,clk,rst,
output reg y);
parameter s0=2'b00,
s1=2'b01,
s2=2'b10,
s3=2'b11;
reg [3:0]state, next_state;
always @(posedge clk or posedge rst)
begin 
if(rst)
 state <= 1'b0;
else
  state <= next_state;
end
always @(*)
begin
case(state)
s0:
if(a)
 next_state = s1;
else
 next_state = s0;
s1:
if(a)
 next_state = s1;
else
 next_state = s2;
s2:
if(a)
 next_state = s3;
else
 next_state = s0;
s3:
if(a)
 next_state = s1;
else
 next_state = s0; 
endcase
end
always @(posedge clk)
begin
if((state == s3)&&(a==1))
 y = 1'b1;
else
 y=1'b0;
end
endmodule

04finite_state_machine/fsm_101/tb_fsm.v
module tb_fsm;
  reg a;
  reg clk,rst;
  wire y;
 fsm uut(
    .a(a),
    .clk(clk),
    .rst(rst),
    .y(y));
  always #5 clk = ~clk;
  initial begin
    $dumpfile("fsm.vcd");
    $dumpvars(0,tb_fsm);
    $monitor("Time=%0t,a=%b,rst=%b,y=%b",$time,a,rst,y);
    clk =0;rst=1;a=1;#10;
    #10 rst = 0;
    a=1;#10;
    a=1;#10;
    a=0;#10;
     a=0;#10;
     a=1;#10;
     a=0;#10;
     a=1;#10;
     a=1;#10;
    $finish;
  end
endmodule

04finite_state_machine/fsm_101/fsm.vcd
$date
	Wed Feb 18 15:42:58 2026
$end
$version
	Icarus Verilog
$end
$timescale
	1s
$end
$scope module tb_fsm $end
$var wire 1 ! y $end
$var reg 1 " a $end
$var reg 1 # clk $end
$var reg 1 $ rst $end
$scope module uut $end
$var wire 1 " a $end
$var wire 1 # clk $end
$var wire 1 $ rst $end
$var parameter 2 % s0 $end
$var parameter 2 & s1 $end
$var parameter 2 ' s2 $end
$var parameter 2 ( s3 $end
$var reg 4 ) next_state [3:0] $end
$var reg 4 * state [3:0] $end
$var reg 1 ! y $end
$upscope $end
$upscope $end
$enddefinitions $end
$comment Show the parameter values. $end
$dumpall
b11 (
b10 '
b1 &
b0 %
$end
#0
$dumpvars
b0 *
b1 )
1$
0#
1"
x!
$end
#5
0!
1#
#10
0#
#15
1#
#20
0#
0$
#25
b1 *
1#
#30
0#
#35
1#
#40
b10 )
0#
0"
#45
b0 )
b10 *
1#
#50
0#
#55
b0 *
1#
#60
b1 )
0#
1"
#65
b1 *
1#
#70
b10 )
0#
0"
#75
b0 )
b10 *
1#
#80
b11 )
0#
1"
#85
b1 )
b11 *
1#
#90
0#
#95
b1 *
1!
1#
