04finite_state_machine/fsm_1101/mooremachine/moore_nonoverlapping.v
module fsm(
  input a,
  input clk,rst,
  output reg y);
  parameter s0=3'b000,
            s1=3'b001,
            s2=3'b010,
            s3=3'b011,
            s4=3'b100;
  reg [3:0]state,next_state;
  always @(posedge clk or posedge rst)
    begin
      if(rst)
        state <= 1'b0;
      else 
        state <= next_state;
    end
  always @(*)begin
    case(state)
      s0: 
        if(a)
          next_state =  s1;
      else
        next_state = s0;
      s1: 
        if(a)
          next_state =  s2;
      else
        next_state = s0;
      s2: 
        if(a)
          next_state =  s2;
      else
        next_state = s3;
      s3: 
        if(a)
          next_state =  s4;
      else
        next_state = s0;
      s4:
      if(a)
        next_state = s1;
      else
        next_state = s0;
      default:next_state= 1'b0;
    endcase
      end
      always @(*)begin
        if(state==s4)
          y=1'b1;
          else
          y= 1'b0;
      
      end
endmodule

04finite_state_machine/fsm_1101/mealymachine/tb_fsm.v
module tb_fsm;
  reg a;
  reg clk,rst;
  wire y;
  fsm uut(
    .a(a),
    .clk(clk),
    .rst(rst),
    .y(y));
  always #5 clk = ~clk;
  initial begin
    $dumpfile("fsm.vcd");
    $dumpvars(0,tb_fsm);
    $monitor("Time=%0t,a=%b,rst=%b,y=%b",$time,a,rst,y);
    clk =0;rst=1;a=1;#10;
    #10 rst = 0;
    a=1;#10;
    a=1;#10;
    a=0;#10;
     a=1;#10;
     a=1;#10;
     a=0;#10;
     a=1;#10;
     a=1;#10;
    $finish;
  end
endmodule

04finite_state_machine/fsm_1101/mooremachine/fsm.vcd
$date
	Sat Feb  7 19:43:48 2026
$end
$version
	Icarus Verilog
$end
$timescale
	1s
$end
$scope module tb_fsm $end
$var wire 1 ! y $end
$var reg 1 " a $end
$var reg 1 # clk $end
$var reg 1 $ rst $end
$scope module uut $end
$var wire 1 " a $end
$var wire 1 # clk $end
$var wire 1 $ rst $end
$var parameter 3 % s0 $end
$var parameter 3 & s1 $end
$var parameter 3 ' s2 $end
$var parameter 3 ( s3 $end
$var parameter 3 ) s4 $end
$var reg 4 * next_state [3:0] $end
$var reg 4 + state [3:0] $end
$var reg 1 ! y $end
$upscope $end
$upscope $end
$enddefinitions $end
$comment Show the parameter values. $end
$dumpall
b100 )
b11 (
b10 '
b1 &
b0 %
$end
#0
$dumpvars
b0 +
b1 *
1$
0#
1"
0!
$end
#5
1#
#10
0#
#15
1#
#20
0#
0$
#25
b10 *
b1 +
1#
#30
0#
#35
b10 +
1#
#40
b11 *
0#
0"
#45
b0 *
b11 +
1#
#50
b100 *
0#
1"
#55
1!
b1 *
b100 +
1#
#60
0#
#65
0!
b10 *
b1 +
1#
#70
b0 *
0#
0"
#75
b0 +
1#
#80
b1 *
0#
1"
#85
b10 *
b1 +
1#
#90
0#
#95
b10 +
1#
